[
  {
    "epoch": 1,
    "train_total": 0.14158158958889544,
    "train_recon": 0.09099706402048469,
    "train_transition": 0.0505845258012414,
    "train_dag": 0.0,
    "train_contrastive": 0.0,
    "val_total": 0.0920683044408049,
    "val_recon": 0.0774296506174973,
    "dag_constraint": 0.0,
    "time_s": 0.2538447380065918
  },
  {
    "epoch": 2,
    "train_total": 0.09784912131726742,
    "train_recon": 0.08656737813726068,
    "train_transition": 0.011281743383733556,
    "train_dag": 0.0,
    "train_contrastive": 0.0,
    "val_total": 0.08224466230188097,
    "val_recon": 0.07499623777610916,
    "dag_constraint": 0.0,
    "time_s": 0.24635934829711914
  },
  {
    "epoch": 3,
    "train_total": 0.09120725118555129,
    "train_recon": 0.0837213434278965,
    "train_transition": 0.0074859075248241425,
    "train_dag": 0.0,
    "train_contrastive": 0.0,
    "val_total": 0.0778648533991405,
    "val_recon": 0.07173436826893262,
    "dag_constraint": 0.0,
    "time_s": 0.2516179084777832
  },
  {
    "epoch": 4,
    "train_total": 0.08591867797076702,
    "train_recon": 0.07894716714508832,
    "train_transition": 0.006971510854782537,
    "train_dag": 0.0,
    "train_contrastive": 0.0,
    "val_total": 0.07343118957110814,
    "val_recon": 0.06709865959627288,
    "dag_constraint": 0.0,
    "time_s": 0.24997806549072266
  },
  {
    "epoch": 5,
    "train_total": 0.07939803204499185,
    "train_recon": 0.07207014714367688,
    "train_transition": 0.007327884653932415,
    "train_dag": 0.0,
    "train_contrastive": 0.0,
    "val_total": 0.06864007136651448,
    "val_recon": 0.061915404562439234,
    "dag_constraint": 0.0,
    "time_s": 0.24657154083251953
  },
  {
    "epoch": 6,
    "train_total": 0.0736739314161241,
    "train_recon": 0.06588012853171676,
    "train_transition": 0.007793803117237985,
    "train_dag": 0.0,
    "train_contrastive": 0.0,
    "val_total": 0.06395437195897102,
    "val_recon": 0.05687115554298673,
    "dag_constraint": 0.0,
    "time_s": 0.24447965621948242
  },
  {
    "epoch": 7,
    "train_total": 0.067959786625579,
    "train_recon": 0.05985076737124473,
    "train_transition": 0.008109018643153831,
    "train_dag": 0.0,
    "train_contrastive": 0.0,
    "val_total": 0.059928243181535175,
    "val_recon": 0.052432531757014136,
    "dag_constraint": 0.0,
    "time_s": 0.24273681640625
  },
  {
    "epoch": 8,
    "train_total": 0.06401842320337892,
    "train_recon": 0.05581255001015961,
    "train_transition": 0.008205873076803982,
    "train_dag": 0.0,
    "train_contrastive": 0.0,
    "val_total": 0.05719496788723128,
    "val_recon": 0.04990727826952934,
    "dag_constraint": 0.0,
    "time_s": 0.25173115730285645
  },
  {
    "epoch": 9,
    "train_total": 0.05933757883030921,
    "train_recon": 0.05122595012653619,
    "train_transition": 0.008111628718324937,
    "train_dag": 0.0,
    "train_contrastive": 0.0,
    "val_total": 0.053656632878950665,
    "val_recon": 0.0463992032621588,
    "dag_constraint": 0.0,
    "time_s": 0.24340581893920898
  },
  {
    "epoch": 10,
    "train_total": 0.0562411448918283,
    "train_recon": 0.04770023131277412,
    "train_transition": 0.008540913579054177,
    "train_dag": 0.0,
    "train_contrastive": 0.0,
    "val_total": 0.05196964155350413,
    "val_recon": 0.04460329030241285,
    "dag_constraint": 0.0,
    "time_s": 0.2494821548461914
  },
  {
    "epoch": 11,
    "train_total": 0.05298603395931423,
    "train_recon": 0.04473024175968021,
    "train_transition": 0.008255792199634016,
    "train_dag": 0.0,
    "train_contrastive": 0.0,
    "val_total": 0.04899411754948752,
    "val_recon": 0.041960309126547406,
    "dag_constraint": 0.0,
    "time_s": 0.24416279792785645
  },
  {
    "epoch": 12,
    "train_total": 0.05014336190652102,
    "train_recon": 0.04205452115274966,
    "train_transition": 0.008088840753771365,
    "train_dag": 0.0,
    "train_contrastive": 0.0,
    "val_total": 0.04763672075101307,
    "val_recon": 0.04032877406903675,
    "dag_constraint": 0.0,
    "time_s": 0.24412131309509277
  },
  {
    "epoch": 13,
    "train_total": 0.04815054195933044,
    "train_recon": 0.040414638235233724,
    "train_transition": 0.0077359035349218175,
    "train_dag": 0.0,
    "train_contrastive": 0.0,
    "val_total": 0.045116666704416275,
    "val_recon": 0.03852953123194831,
    "dag_constraint": 0.0,
    "time_s": 0.25154614448547363
  },
  {
    "epoch": 14,
    "train_total": 0.0456617308082059,
    "train_recon": 0.038110633846372366,
    "train_transition": 0.007551096816314384,
    "train_dag": 0.0,
    "train_contrastive": 0.0,
    "val_total": 0.04325919970870018,
    "val_recon": 0.03678382134863308,
    "dag_constraint": 0.0,
    "time_s": 0.24489688873291016
  },
  {
    "epoch": 15,
    "train_total": 0.04394597955979407,
    "train_recon": 0.036473368178121746,
    "train_transition": 0.007472611410776153,
    "train_dag": 0.0,
    "train_contrastive": 0.0,
    "val_total": 0.042226744549615045,
    "val_recon": 0.03589781852705138,
    "dag_constraint": 0.0,
    "time_s": 0.24512195587158203
  },
  {
    "epoch": 16,
    "train_total": 0.041862065554596484,
    "train_recon": 0.03464963473379612,
    "train_transition": 0.007212430602521636,
    "train_dag": 0.0,
    "train_contrastive": 0.0,
    "val_total": 0.04163296041744096,
    "val_recon": 0.035793253885848184,
    "dag_constraint": 0.0,
    "time_s": 0.24961280822753906
  },
  {
    "epoch": 17,
    "train_total": 0.04094136622734368,
    "train_recon": 0.03410856262780726,
    "train_transition": 0.006832803614088334,
    "train_dag": 0.0,
    "train_contrastive": 0.0,
    "val_total": 0.04036980388419969,
    "val_recon": 0.03433404304087162,
    "dag_constraint": 0.0,
    "time_s": 0.24322128295898438
  },
  {
    "epoch": 18,
    "train_total": 0.039444683759938926,
    "train_recon": 0.03282530006254092,
    "train_transition": 0.00661938387202099,
    "train_dag": 0.0,
    "train_contrastive": 0.0,
    "val_total": 0.03862226328679493,
    "val_recon": 0.03268294009779181,
    "dag_constraint": 0.0,
    "time_s": 0.2442162036895752
  },
  {
    "epoch": 19,
    "train_total": 0.038398402743041515,
    "train_recon": 0.03187747951596975,
    "train_transition": 0.0065209234453504905,
    "train_dag": 0.0,
    "train_contrastive": 0.0,
    "val_total": 0.037701459867613654,
    "val_recon": 0.03223901800811291,
    "dag_constraint": 0.0,
    "time_s": 0.24393200874328613
  },
  {
    "epoch": 20,
    "train_total": 0.037259874399751425,
    "train_recon": 0.030961363576352596,
    "train_transition": 0.006298510852502659,
    "train_dag": 0.0,
    "train_contrastive": 0.0,
    "val_total": 0.03688002856714385,
    "val_recon": 0.03141938602285726,
    "dag_constraint": 0.0,
    "time_s": 0.24662041664123535
  },
  {
    "epoch": 21,
    "train_total": 0.036536207189783454,
    "train_recon": 0.030414725188165903,
    "train_transition": 0.006121481870650314,
    "train_dag": 0.0,
    "train_contrastive": 0.0,
    "val_total": 0.03662137101803507,
    "val_recon": 0.031348761171102524,
    "dag_constraint": 0.0,
    "time_s": 0.25018739700317383
  },
  {
    "epoch": 22,
    "train_total": 0.03586025955155492,
    "train_recon": 0.02991037437459454,
    "train_transition": 0.0059498850896488875,
    "train_dag": 0.0,
    "train_contrastive": 0.0,
    "val_total": 0.03620737258877073,
    "val_recon": 0.03103169665804931,
    "dag_constraint": 0.0,
    "time_s": 0.2492961883544922
  },
  {
    "epoch": 23,
    "train_total": 0.03538978530559689,
    "train_recon": 0.029595562140457332,
    "train_transition": 0.005794223019620404,
    "train_dag": 0.0,
    "train_contrastive": 0.0,
    "val_total": 0.035521269376788824,
    "val_recon": 0.030467519802706584,
    "dag_constraint": 0.0,
    "time_s": 0.2534797191619873
  },
  {
    "epoch": 24,
    "train_total": 0.034816007129848,
    "train_recon": 0.029266091820318252,
    "train_transition": 0.005549915425945073,
    "train_dag": 0.0,
    "train_contrastive": 0.0,
    "val_total": 0.03443199768662453,
    "val_recon": 0.029615184824381555,
    "dag_constraint": 0.0,
    "time_s": 0.2523503303527832
  },
  {
    "epoch": 25,
    "train_total": 0.034018577367533,
    "train_recon": 0.02864713198505342,
    "train_transition": 0.005371445367927663,
    "train_dag": 0.0,
    "train_contrastive": 0.0,
    "val_total": 0.03431818900363786,
    "val_recon": 0.029560354139123644,
    "dag_constraint": 0.0,
    "time_s": 0.24119162559509277
  },
  {
    "epoch": 26,
    "train_total": 0.03379404009319842,
    "train_recon": 0.028595192881766707,
    "train_transition": 0.005198847386054695,
    "train_dag": 0.0,
    "train_contrastive": 0.0,
    "val_total": 0.034387294735227315,
    "val_recon": 0.029779859153287753,
    "dag_constraint": 0.0,
    "time_s": 0.24330902099609375
  },
  {
    "epoch": 27,
    "train_total": 0.03358787705656141,
    "train_recon": 0.0285141384229064,
    "train_transition": 0.00507373851723969,
    "train_dag": 0.0,
    "train_contrastive": 0.0,
    "val_total": 0.03466563086424555,
    "val_recon": 0.029999185353517532,
    "dag_constraint": 0.0,
    "time_s": 0.24236583709716797
  },
  {
    "epoch": 28,
    "train_total": 0.033004447526764125,
    "train_recon": 0.02804803167236969,
    "train_transition": 0.0049564157670829445,
    "train_dag": 0.0,
    "train_contrastive": 0.0,
    "val_total": 0.03325616781200681,
    "val_recon": 0.028934423412595476,
    "dag_constraint": 0.0,
    "time_s": 0.2502152919769287
  },
  {
    "epoch": 29,
    "train_total": 0.03274489945033565,
    "train_recon": 0.028035186580382288,
    "train_transition": 0.004709712666226551,
    "train_dag": 0.0,
    "train_contrastive": 0.0,
    "val_total": 0.033056563298617093,
    "val_recon": 0.02878938615322113,
    "dag_constraint": 0.0,
    "time_s": 0.25078487396240234
  },
  {
    "epoch": 30,
    "train_total": 0.03232373099308461,
    "train_recon": 0.027700641832780093,
    "train_transition": 0.004623089262167923,
    "train_dag": 0.0,
    "train_contrastive": 0.0,
    "val_total": 0.03343790290611131,
    "val_recon": 0.029311655621443476,
    "dag_constraint": 0.0,
    "time_s": 0.24515342712402344
  },
  {
    "epoch": 31,
    "train_total": 0.03269480913877487,
    "train_recon": 0.028141950780991465,
    "train_transition": 0.004552858270471916,
    "train_dag": 0.0,
    "train_contrastive": 0.0,
    "val_total": 0.03285478640879903,
    "val_recon": 0.02893125664974962,
    "dag_constraint": 0.0,
    "time_s": 0.24895095825195312
  },
  {
    "epoch": 32,
    "train_total": 0.03194671217352152,
    "train_recon": 0.027579893299844116,
    "train_transition": 0.00436681869905442,
    "train_dag": 0.0,
    "train_contrastive": 0.0,
    "val_total": 0.03234827225761754,
    "val_recon": 0.028432945321713175,
    "dag_constraint": 0.0,
    "time_s": 0.25128674507141113
  },
  {
    "epoch": 33,
    "train_total": 0.03311352146556601,
    "train_recon": 0.02881475235335529,
    "train_transition": 0.004298769330489449,
    "train_dag": 0.0,
    "train_contrastive": 0.0,
    "val_total": 0.03521863903318133,
    "val_recon": 0.031035288370081356,
    "dag_constraint": 0.0,
    "time_s": 0.2487931251525879
  },
  {
    "epoch": 34,
    "train_total": 0.03284746123244986,
    "train_recon": 0.028578962665051222,
    "train_transition": 0.0042684984364314005,
    "train_dag": 0.0,
    "train_contrastive": 0.0,
    "val_total": 0.032076994223254066,
    "val_recon": 0.028380537405610085,
    "dag_constraint": 0.0,
    "time_s": 0.25037121772766113
  },
  {
    "epoch": 35,
    "train_total": 0.03106861177366227,
    "train_recon": 0.027067696559242904,
    "train_transition": 0.004000915432698093,
    "train_dag": 0.0,
    "train_contrastive": 0.0,
    "val_total": 0.032771097496151924,
    "val_recon": 0.029005943132298335,
    "dag_constraint": 0.0,
    "time_s": 0.24691534042358398
  },
  {
    "epoch": 36,
    "train_total": 0.031282193725928664,
    "train_recon": 0.027247498161159456,
    "train_transition": 0.004034695535665378,
    "train_dag": 0.0,
    "train_contrastive": 0.0,
    "val_total": 0.032077573505895476,
    "val_recon": 0.028431212263447896,
    "dag_constraint": 0.0,
    "time_s": 0.24562883377075195
  },
  {
    "epoch": 37,
    "train_total": 0.030735080421436578,
    "train_recon": 0.026884225895628333,
    "train_transition": 0.0038508546713273972,
    "train_dag": 0.0,
    "train_contrastive": 0.0,
    "val_total": 0.03229563257523945,
    "val_recon": 0.02883352286049298,
    "dag_constraint": 0.0,
    "time_s": 0.24591541290283203
  },
  {
    "epoch": 38,
    "train_total": 0.03063968481728807,
    "train_recon": 0.026845764776226133,
    "train_transition": 0.003793920055613853,
    "train_dag": 0.0,
    "train_contrastive": 0.0,
    "val_total": 0.03265707141586712,
    "val_recon": 0.029233947130186216,
    "dag_constraint": 0.0,
    "time_s": 0.2455310821533203
  },
  {
    "epoch": 39,
    "train_total": 0.0306715895421803,
    "train_recon": 0.02692989440402016,
    "train_transition": 0.003741695123608224,
    "train_dag": 0.0,
    "train_contrastive": 0.0,
    "val_total": 0.031921950834138055,
    "val_recon": 0.028684414391006743,
    "dag_constraint": 0.0,
    "time_s": 0.2441396713256836
  },
  {
    "epoch": 40,
    "train_total": 0.03060985915362835,
    "train_recon": 0.027014996972866356,
    "train_transition": 0.0035948622826253995,
    "train_dag": 0.0,
    "train_contrastive": 0.0,
    "val_total": 0.0310712427433048,
    "val_recon": 0.027891202430639948,
    "dag_constraint": 0.0,
    "time_s": 0.24294829368591309
  },
  {
    "epoch": 41,
    "train_total": 0.030225481430534273,
    "train_recon": 0.026667076628655195,
    "train_transition": 0.00355840461270418,
    "train_dag": 0.0,
    "train_contrastive": 0.0,
    "val_total": 0.03210906923881599,
    "val_recon": 0.028935963554041728,
    "dag_constraint": 0.0,
    "time_s": 0.24576759338378906
  },
  {
    "epoch": 42,
    "train_total": 0.030164663796313107,
    "train_recon": 0.026701117167249322,
    "train_transition": 0.0034635466436157003,
    "train_dag": 0.0,
    "train_contrastive": 0.0,
    "val_total": 0.03162927366793156,
    "val_recon": 0.02850881591439247,
    "dag_constraint": 0.0,
    "time_s": 0.2449350357055664
  },
  {
    "epoch": 43,
    "train_total": 0.030024695035535842,
    "train_recon": 0.026627351413480937,
    "train_transition": 0.0033973434765357524,
    "train_dag": 0.0,
    "train_contrastive": 0.0,
    "val_total": 0.0318188550216811,
    "val_recon": 0.02875265958053725,
    "dag_constraint": 0.0,
    "time_s": 0.24158930778503418
  },
  {
    "epoch": 44,
    "train_total": 0.030195125669706613,
    "train_recon": 0.026797590486239642,
    "train_transition": 0.003397535256226547,
    "train_dag": 0.0,
    "train_contrastive": 0.0,
    "val_total": 0.03130268332149301,
    "val_recon": 0.028289496898651123,
    "dag_constraint": 0.0,
    "time_s": 0.244964599609375
  },
  {
    "epoch": 45,
    "train_total": 0.029814718116540462,
    "train_recon": 0.026527063513640314,
    "train_transition": 0.0032876546756597236,
    "train_dag": 0.0,
    "train_contrastive": 0.0,
    "val_total": 0.03165055784795966,
    "val_recon": 0.028669843716280802,
    "dag_constraint": 0.0,
    "time_s": 0.24523615837097168
  },
  {
    "epoch": 46,
    "train_total": 0.029618700908031315,
    "train_recon": 0.02639685437316075,
    "train_transition": 0.003221846360247582,
    "train_dag": 0.0,
    "train_contrastive": 0.0,
    "val_total": 0.030968578000153815,
    "val_recon": 0.027981258928775787,
    "dag_constraint": 0.0,
    "time_s": 0.24852681159973145
  },
  {
    "epoch": 47,
    "train_total": 0.030441313749179244,
    "train_recon": 0.027233842585701495,
    "train_transition": 0.003207471381756477,
    "train_dag": 0.0,
    "train_contrastive": 0.0,
    "val_total": 0.032444478145667484,
    "val_recon": 0.029522006266883442,
    "dag_constraint": 0.0,
    "time_s": 0.24373459815979004
  },
  {
    "epoch": 48,
    "train_total": 0.030125447316095233,
    "train_recon": 0.026982699113432318,
    "train_transition": 0.0031427481153514236,
    "train_dag": 0.0,
    "train_contrastive": 0.0,
    "val_total": 0.030742149001785686,
    "val_recon": 0.02786642632314137,
    "dag_constraint": 0.0,
    "time_s": 0.2439117431640625
  },
  {
    "epoch": 49,
    "train_total": 0.029206312086898834,
    "train_recon": 0.026154847291763872,
    "train_transition": 0.003051464882446453,
    "train_dag": 0.0,
    "train_contrastive": 0.0,
    "val_total": 0.030419728053467616,
    "val_recon": 0.027608823031187057,
    "dag_constraint": 0.0,
    "time_s": 0.24678802490234375
  },
  {
    "epoch": 50,
    "train_total": 0.029363040637690574,
    "train_recon": 0.026281868340447545,
    "train_transition": 0.0030811724573140964,
    "train_dag": 0.0,
    "train_contrastive": 0.0,
    "val_total": 0.03156151968453612,
    "val_recon": 0.02880928585571902,
    "dag_constraint": 0.0,
    "time_s": 0.24533462524414062
  },
  {
    "epoch": 51,
    "train_total": 0.029804163437802345,
    "train_recon": 0.026770347671117634,
    "train_transition": 0.0030338157957885414,
    "train_dag": 0.0,
    "train_contrastive": 0.0,
    "val_total": 0.030574978994471685,
    "val_recon": 0.02793252601155213,
    "dag_constraint": 0.0,
    "time_s": 0.24425268173217773
  },
  {
    "epoch": 52,
    "train_total": 0.02948292373912409,
    "train_recon": 0.02655076963128522,
    "train_transition": 0.0029321540641831234,
    "train_dag": 0.0,
    "train_contrastive": 0.0,
    "val_total": 0.030152113043836186,
    "val_recon": 0.027531477489641736,
    "dag_constraint": 0.0,
    "time_s": 0.24698209762573242
  },
  {
    "epoch": 53,
    "train_total": 0.029633985250256956,
    "train_recon": 0.026669635728467256,
    "train_transition": 0.0029643495217897,
    "train_dag": 0.0,
    "train_contrastive": 0.0,
    "val_total": 0.03188291537974562,
    "val_recon": 0.029116514271923473,
    "dag_constraint": 0.0,
    "time_s": 0.24850082397460938
  },
  {
    "epoch": 54,
    "train_total": 0.029786361090373248,
    "train_recon": 0.02689813292818144,
    "train_transition": 0.0028882280603284016,
    "train_dag": 0.0,
    "train_contrastive": 0.0,
    "val_total": 0.030443044379353523,
    "val_recon": 0.027873041374342784,
    "dag_constraint": 0.0,
    "time_s": 0.24805760383605957
  },
  {
    "epoch": 55,
    "train_total": 0.028814721561502665,
    "train_recon": 0.026017978438176215,
    "train_transition": 0.002796743458020501,
    "train_dag": 0.0,
    "train_contrastive": 0.0,
    "val_total": 0.03035949170589447,
    "val_recon": 0.0276245011815003,
    "dag_constraint": 0.0,
    "time_s": 0.24300670623779297
  },
  {
    "epoch": 56,
    "train_total": 0.028794659359846264,
    "train_recon": 0.0259698843001388,
    "train_transition": 0.0028247748996363953,
    "train_dag": 0.0,
    "train_contrastive": 0.0,
    "val_total": 0.0297747262354408,
    "val_recon": 0.027183298287647113,
    "dag_constraint": 0.0,
    "time_s": 0.24753999710083008
  },
  {
    "epoch": 57,
    "train_total": 0.028788061521481723,
    "train_recon": 0.02607391739729792,
    "train_transition": 0.0027141442405991256,
    "train_dag": 0.0,
    "train_contrastive": 0.0,
    "val_total": 0.03056530494775091,
    "val_recon": 0.028070920812232152,
    "dag_constraint": 0.0,
    "time_s": 0.24442148208618164
  },
  {
    "epoch": 58,
    "train_total": 0.0291429859935306,
    "train_recon": 0.026432754239067435,
    "train_transition": 0.002710231754463166,
    "train_dag": 0.0,
    "train_contrastive": 0.0,
    "val_total": 0.029717639620815004,
    "val_recon": 0.027233449476105825,
    "dag_constraint": 0.0,
    "time_s": 0.24515795707702637
  },
  {
    "epoch": 59,
    "train_total": 0.02885637991130352,
    "train_recon": 0.02615715144202113,
    "train_transition": 0.0026992284547304735,
    "train_dag": 0.0,
    "train_contrastive": 0.0,
    "val_total": 0.03129815948860986,
    "val_recon": 0.028716813506824628,
    "dag_constraint": 0.0,
    "time_s": 0.24434137344360352
  },
  {
    "epoch": 60,
    "train_total": 0.029405129025690258,
    "train_recon": 0.026701479742769152,
    "train_transition": 0.0027036492683691904,
    "train_dag": 0.0,
    "train_contrastive": 0.0,
    "val_total": 0.02971609788281577,
    "val_recon": 0.027354053354689052,
    "dag_constraint": 0.0,
    "time_s": 0.24422383308410645
  },
  {
    "epoch": 61,
    "train_total": 0.02840928389923647,
    "train_recon": 0.025853975559584796,
    "train_transition": 0.0025553081795806065,
    "train_dag": 0.0,
    "train_contrastive": 0.0,
    "val_total": 0.030182390340736935,
    "val_recon": 0.027696248410003527,
    "dag_constraint": 0.0,
    "time_s": 0.24715399742126465
  },
  {
    "epoch": 62,
    "train_total": 0.028615622431971133,
    "train_recon": 0.025986777036450803,
    "train_transition": 0.0026288455992471427,
    "train_dag": 0.0,
    "train_contrastive": 0.0,
    "val_total": 0.030231890667762076,
    "val_recon": 0.02788190809743745,
    "dag_constraint": 0.0,
    "time_s": 0.24688100814819336
  },
  {
    "epoch": 63,
    "train_total": 0.028709562437143177,
    "train_recon": 0.026176319108344615,
    "train_transition": 0.0025332431687274948,
    "train_dag": 0.0,
    "train_contrastive": 0.0,
    "val_total": 0.031243992171117237,
    "val_recon": 0.02873121734176363,
    "dag_constraint": 0.0,
    "time_s": 0.2590932846069336
  },
  {
    "epoch": 64,
    "train_total": 0.029100323445163667,
    "train_recon": 0.026525222114287317,
    "train_transition": 0.0025751014763955027,
    "train_dag": 0.0,
    "train_contrastive": 0.0,
    "val_total": 0.0296112165919372,
    "val_recon": 0.02723814786544868,
    "dag_constraint": 0.0,
    "time_s": 0.25243330001831055
  },
  {
    "epoch": 65,
    "train_total": 0.028586546482983977,
    "train_recon": 0.026023799611721188,
    "train_transition": 0.0025627469731261954,
    "train_dag": 0.0,
    "train_contrastive": 0.0,
    "val_total": 0.03014812432229519,
    "val_recon": 0.02778986096382141,
    "dag_constraint": 0.0,
    "time_s": 0.2533280849456787
  },
  {
    "epoch": 66,
    "train_total": 0.028287832159548998,
    "train_recon": 0.02580683451378718,
    "train_transition": 0.002480997849488631,
    "train_dag": 0.0,
    "train_contrastive": 0.0,
    "val_total": 0.029256008565425873,
    "val_recon": 0.026949590604220117,
    "dag_constraint": 0.0,
    "time_s": 0.2501978874206543
  },
  {
    "epoch": 67,
    "train_total": 0.028255071549210697,
    "train_recon": 0.02578849613200873,
    "train_transition": 0.002466575475409627,
    "train_dag": 0.0,
    "train_contrastive": 0.0,
    "val_total": 0.030090907854693278,
    "val_recon": 0.02780097190822874,
    "dag_constraint": 0.0,
    "time_s": 0.24668622016906738
  },
  {
    "epoch": 68,
    "train_total": 0.02814539521932602,
    "train_recon": 0.025705847481731325,
    "train_transition": 0.002439547926769592,
    "train_dag": 0.0,
    "train_contrastive": 0.0,
    "val_total": 0.02989159577659198,
    "val_recon": 0.027569737285375595,
    "dag_constraint": 0.0,
    "time_s": 0.24468183517456055
  },
  {
    "epoch": 69,
    "train_total": 0.028073169756680727,
    "train_recon": 0.025660219660494477,
    "train_transition": 0.0024129500816343352,
    "train_dag": 0.0,
    "train_contrastive": 0.0,
    "val_total": 0.029220722349626676,
    "val_recon": 0.027078681492379734,
    "dag_constraint": 0.0,
    "time_s": 0.2561211585998535
  },
  {
    "epoch": 70,
    "train_total": 0.027937687875237316,
    "train_recon": 0.025566157593857497,
    "train_transition": 0.002371530223172158,
    "train_dag": 0.0,
    "train_contrastive": 0.0,
    "val_total": 0.031128465863210813,
    "val_recon": 0.028832075585212027,
    "dag_constraint": 0.0,
    "time_s": 0.24599623680114746
  },
  {
    "epoch": 71,
    "train_total": 0.028154841857030988,
    "train_recon": 0.025805236538872123,
    "train_transition": 0.0023496051435358822,
    "train_dag": 0.0,
    "train_contrastive": 0.0,
    "val_total": 0.029626227649194852,
    "val_recon": 0.027439145371317863,
    "dag_constraint": 0.0,
    "time_s": 0.24525904655456543
  },
  {
    "epoch": 72,
    "train_total": 0.027878010412678123,
    "train_recon": 0.02555395243689418,
    "train_transition": 0.0023240580485435203,
    "train_dag": 0.0,
    "train_contrastive": 0.0,
    "val_total": 0.029206142893859317,
    "val_recon": 0.027015523985028267,
    "dag_constraint": 0.0,
    "time_s": 0.24842309951782227
  },
  {
    "epoch": 73,
    "train_total": 0.027694037125911564,
    "train_recon": 0.02538595104124397,
    "train_transition": 0.002308086128323339,
    "train_dag": 0.0,
    "train_contrastive": 0.0,
    "val_total": 0.03020032974226134,
    "val_recon": 0.027928277584058896,
    "dag_constraint": 0.0,
    "time_s": 0.24950599670410156
  },
  {
    "epoch": 74,
    "train_total": 0.0277466734405607,
    "train_recon": 0.02549576567253098,
    "train_transition": 0.002250907782581635,
    "train_dag": 0.0,
    "train_contrastive": 0.0,
    "val_total": 0.0301606362419469,
    "val_recon": 0.02795086375304631,
    "dag_constraint": 0.0,
    "time_s": 0.24152708053588867
  },
  {
    "epoch": 75,
    "train_total": 0.027790640364401042,
    "train_recon": 0.025500126532278955,
    "train_transition": 0.0022905137739144266,
    "train_dag": 0.0,
    "train_contrastive": 0.0,
    "val_total": 0.028825209609099796,
    "val_recon": 0.02671243729335921,
    "dag_constraint": 0.0,
    "time_s": 0.24131369590759277
  },
  {
    "epoch": 76,
    "train_total": 0.027676128782331944,
    "train_recon": 0.025493903842289,
    "train_transition": 0.0021822249400429428,
    "train_dag": 0.0,
    "train_contrastive": 0.0,
    "val_total": 0.029897021928003857,
    "val_recon": 0.027740035206079483,
    "dag_constraint": 0.0,
    "time_s": 0.24091267585754395
  },
  {
    "epoch": 77,
    "train_total": 0.028236053069122136,
    "train_recon": 0.025967440742533654,
    "train_transition": 0.002268612399348058,
    "train_dag": 0.0,
    "train_contrastive": 0.0,
    "val_total": 0.02896274732691901,
    "val_recon": 0.026820371193545207,
    "dag_constraint": 0.0,
    "time_s": 0.24710917472839355
  },
  {
    "epoch": 78,
    "train_total": 0.02741554827662185,
    "train_recon": 0.025218915368895978,
    "train_transition": 0.0021966329513816163,
    "train_dag": 0.0,
    "train_contrastive": 0.0,
    "val_total": 0.029843115913016454,
    "val_recon": 0.02773349093539374,
    "dag_constraint": 0.0,
    "time_s": 0.2528553009033203
  },
  {
    "epoch": 79,
    "train_total": 0.027728476678021252,
    "train_recon": 0.02554416161729023,
    "train_transition": 0.002184314958867617,
    "train_dag": 0.0,
    "train_contrastive": 0.0,
    "val_total": 0.02889711649290153,
    "val_recon": 0.02691021854324,
    "dag_constraint": 0.0,
    "time_s": 0.2504403591156006
  },
  {
    "epoch": 80,
    "train_total": 0.02750405325787142,
    "train_recon": 0.025365891749970615,
    "train_transition": 0.002138161667971872,
    "train_dag": 0.0,
    "train_contrastive": 0.0,
    "val_total": 0.028875243983098438,
    "val_recon": 0.02682752987103803,
    "dag_constraint": 0.0,
    "time_s": 0.2530026435852051
  },
  {
    "epoch": 81,
    "train_total": 0.0273834370309487,
    "train_recon": 0.025241295632440597,
    "train_transition": 0.0021421415149234235,
    "train_dag": 0.0,
    "train_contrastive": 0.0,
    "val_total": 0.028647488515291895,
    "val_recon": 0.02664850971528462,
    "dag_constraint": 0.0,
    "time_s": 0.2517728805541992
  },
  {
    "epoch": 82,
    "train_total": 0.027721462887711823,
    "train_recon": 0.025548949546646327,
    "train_transition": 0.002172513326513581,
    "train_dag": 0.0,
    "train_contrastive": 0.0,
    "val_total": 0.029371915119034902,
    "val_recon": 0.02740164686526571,
    "dag_constraint": 0.0,
    "time_s": 0.2506070137023926
  },
  {
    "epoch": 83,
    "train_total": 0.02778789185686037,
    "train_recon": 0.025675667566247284,
    "train_transition": 0.002112224537995644,
    "train_dag": 0.0,
    "train_contrastive": 0.0,
    "val_total": 0.029466827799166952,
    "val_recon": 0.02748453484049865,
    "dag_constraint": 0.0,
    "time_s": 0.2492074966430664
  },
  {
    "epoch": 84,
    "train_total": 0.02759408630663529,
    "train_recon": 0.02548224845668301,
    "train_transition": 0.0021118378645041957,
    "train_dag": 0.0,
    "train_contrastive": 0.0,
    "val_total": 0.029027889349630902,
    "val_recon": 0.027013946856771196,
    "dag_constraint": 0.0,
    "time_s": 0.24647164344787598
  },
  {
    "epoch": 85,
    "train_total": 0.02772862371057272,
    "train_recon": 0.025600764900445938,
    "train_transition": 0.0021278588101267815,
    "train_dag": 0.0,
    "train_contrastive": 0.0,
    "val_total": 0.029921466218573705,
    "val_recon": 0.027908097952604294,
    "dag_constraint": 0.0,
    "time_s": 0.24282360076904297
  },
  {
    "epoch": 86,
    "train_total": 0.02788620220962912,
    "train_recon": 0.025779707299079746,
    "train_transition": 0.0021064950415166095,
    "train_dag": 0.0,
    "train_contrastive": 0.0,
    "val_total": 0.02889091175581728,
    "val_recon": 0.02697728467839105,
    "dag_constraint": 0.0,
    "time_s": 0.2455735206604004
  },
  {
    "epoch": 87,
    "train_total": 0.0278496170649305,
    "train_recon": 0.02575614640954882,
    "train_transition": 0.002093470626277849,
    "train_dag": 0.0,
    "train_contrastive": 0.0,
    "val_total": 0.030202107237918035,
    "val_recon": 0.028139252747808183,
    "dag_constraint": 0.0,
    "time_s": 0.24310779571533203
  },
  {
    "epoch": 88,
    "train_total": 0.027956295874901116,
    "train_recon": 0.025880708126351237,
    "train_transition": 0.0020755878795171157,
    "train_dag": 0.0,
    "train_contrastive": 0.0,
    "val_total": 0.028422863089612553,
    "val_recon": 0.026457399928144047,
    "dag_constraint": 0.0,
    "time_s": 0.24342584609985352
  },
  {
    "epoch": 89,
    "train_total": 0.027472478337585926,
    "train_recon": 0.02541448560077697,
    "train_transition": 0.002057992809568532,
    "train_dag": 0.0,
    "train_contrastive": 0.0,
    "val_total": 0.02902000610317503,
    "val_recon": 0.027091389255864278,
    "dag_constraint": 0.0,
    "time_s": 0.24362993240356445
  },
  {
    "epoch": 90,
    "train_total": 0.02743754640687257,
    "train_recon": 0.025416448479518294,
    "train_transition": 0.002021098043769598,
    "train_dag": 0.0,
    "train_contrastive": 0.0,
    "val_total": 0.029060418052332743,
    "val_recon": 0.02713108036134924,
    "dag_constraint": 0.0,
    "time_s": 0.23891377449035645
  },
  {
    "epoch": 91,
    "train_total": 0.028226912254467607,
    "train_recon": 0.02617195330094546,
    "train_transition": 0.0020549589971778914,
    "train_dag": 0.0,
    "train_contrastive": 0.0,
    "val_total": 0.0305829183863742,
    "val_recon": 0.028530349422778403,
    "dag_constraint": 0.0,
    "time_s": 0.24109625816345215
  },
  {
    "epoch": 92,
    "train_total": 0.027705193613655865,
    "train_recon": 0.025648590293712914,
    "train_transition": 0.0020566032908391207,
    "train_dag": 0.0,
    "train_contrastive": 0.0,
    "val_total": 0.029513444751501083,
    "val_recon": 0.027498736179300716,
    "dag_constraint": 0.0,
    "time_s": 0.2409665584564209
  },
  {
    "epoch": 93,
    "train_total": 0.027239521616138518,
    "train_recon": 0.025211666070390493,
    "train_transition": 0.0020278555020922795,
    "train_dag": 0.0,
    "train_contrastive": 0.0,
    "val_total": 0.028659922736031667,
    "val_recon": 0.02678529066698892,
    "dag_constraint": 0.0,
    "time_s": 0.24545931816101074
  },
  {
    "epoch": 94,
    "train_total": 0.027632708137389272,
    "train_recon": 0.025623951922170818,
    "train_transition": 0.002008756360737607,
    "train_dag": 0.0,
    "train_contrastive": 0.0,
    "val_total": 0.02910601587167808,
    "val_recon": 0.02723721893770354,
    "dag_constraint": 0.0,
    "time_s": 0.24135589599609375
  },
  {
    "epoch": 95,
    "train_total": 0.027109854796435684,
    "train_recon": 0.02512796875089407,
    "train_transition": 0.0019818861183011904,
    "train_dag": 0.0,
    "train_contrastive": 0.0,
    "val_total": 0.029256029586706842,
    "val_recon": 0.027378253106560026,
    "dag_constraint": 0.0,
    "time_s": 0.24013519287109375
  },
  {
    "epoch": 96,
    "train_total": 0.027251421357505023,
    "train_recon": 0.02527540095616132,
    "train_transition": 0.00197602050320711,
    "train_dag": 0.0,
    "train_contrastive": 0.0,
    "val_total": 0.02922853029200009,
    "val_recon": 0.027401318241442953,
    "dag_constraint": 0.0,
    "time_s": 0.24182629585266113
  },
  {
    "epoch": 97,
    "train_total": 0.02762909501325339,
    "train_recon": 0.025681464350782335,
    "train_transition": 0.001947630720678717,
    "train_dag": 0.0,
    "train_contrastive": 0.0,
    "val_total": 0.02915267433438982,
    "val_recon": 0.0272892386253391,
    "dag_constraint": 0.0,
    "time_s": 0.24556803703308105
  },
  {
    "epoch": 98,
    "train_total": 0.02736705227289349,
    "train_recon": 0.025399992242455482,
    "train_transition": 0.001967060088645667,
    "train_dag": 0.0,
    "train_contrastive": 0.0,
    "val_total": 0.02866907843521663,
    "val_recon": 0.02684449910053185,
    "dag_constraint": 0.0,
    "time_s": 0.24320030212402344
  },
  {
    "epoch": 99,
    "train_total": 0.02698309876723215,
    "train_recon": 0.02506825333693996,
    "train_transition": 0.00191484548849985,
    "train_dag": 0.0,
    "train_contrastive": 0.0,
    "val_total": 0.02903399510043008,
    "val_recon": 0.027221170121005604,
    "dag_constraint": 0.0,
    "time_s": 0.24637413024902344
  },
  {
    "epoch": 100,
    "train_total": 0.027004090428818017,
    "train_recon": 0.025086221285164356,
    "train_transition": 0.0019178690708940849,
    "train_dag": 0.0,
    "train_contrastive": 0.0,
    "val_total": 0.02888231405190059,
    "val_recon": 0.027016338759234974,
    "dag_constraint": 0.0,
    "time_s": 0.24756789207458496
  },
  {
    "epoch": 101,
    "train_total": 0.0269656969467178,
    "train_recon": 0.0250478814705275,
    "train_transition": 0.0019178153161192313,
    "train_dag": 0.0,
    "train_contrastive": 0.0,
    "val_total": 0.028805735920156752,
    "val_recon": 0.026968209339039668,
    "dag_constraint": 0.0,
    "time_s": 0.24763250350952148
  },
  {
    "epoch": 102,
    "train_total": 0.02718593063764274,
    "train_recon": 0.02529113442869857,
    "train_transition": 0.0018947961798403412,
    "train_dag": 0.0,
    "train_contrastive": 0.0,
    "val_total": 0.028454483087573732,
    "val_recon": 0.026667163308177675,
    "dag_constraint": 0.0,
    "time_s": 0.24083995819091797
  },
  {
    "epoch": 103,
    "train_total": 0.026919337222352624,
    "train_recon": 0.025017414998728782,
    "train_transition": 0.001901922354591079,
    "train_dag": 0.0,
    "train_contrastive": 0.0,
    "val_total": 0.02875669300556183,
    "val_recon": 0.026865569076367786,
    "dag_constraint": 0.0,
    "time_s": 0.25061964988708496
  },
  {
    "epoch": 104,
    "train_total": 0.02723371534375474,
    "train_recon": 0.025346522917971015,
    "train_transition": 0.001887192323920317,
    "train_dag": 0.0,
    "train_contrastive": 0.0,
    "val_total": 0.0291797151522977,
    "val_recon": 0.02740066232425826,
    "dag_constraint": 0.0,
    "time_s": 0.25448131561279297
  },
  {
    "epoch": 105,
    "train_total": 0.02717109606601298,
    "train_recon": 0.02530682517681271,
    "train_transition": 0.0018642709328560159,
    "train_dag": 0.0,
    "train_contrastive": 0.0,
    "val_total": 0.028730126097798347,
    "val_recon": 0.026958721024649485,
    "dag_constraint": 0.0,
    "time_s": 0.24701189994812012
  },
  {
    "epoch": 106,
    "train_total": 0.026793733122758567,
    "train_recon": 0.024955669476184994,
    "train_transition": 0.0018380636756774038,
    "train_dag": 0.0,
    "train_contrastive": 0.0,
    "val_total": 0.02918328797178609,
    "val_recon": 0.027378345972725322,
    "dag_constraint": 0.0,
    "time_s": 0.24287700653076172
  },
  {
    "epoch": 107,
    "train_total": 0.026941216143313795,
    "train_recon": 0.02510425535729155,
    "train_transition": 0.0018369608878856525,
    "train_dag": 0.0,
    "train_contrastive": 0.0,
    "val_total": 0.028730605063693865,
    "val_recon": 0.026985300704836845,
    "dag_constraint": 0.0,
    "time_s": 0.23964452743530273
  },
  {
    "epoch": 108,
    "train_total": 0.026672935695387423,
    "train_recon": 0.024834891606587917,
    "train_transition": 0.001838044190662913,
    "train_dag": 0.0,
    "train_contrastive": 0.0,
    "val_total": 0.028571521331157004,
    "val_recon": 0.026890859273927554,
    "dag_constraint": 0.0,
    "time_s": 0.23842883110046387
  }
]