[
  {
    "epoch": 1,
    "train_total": 0.19575508730486035,
    "train_recon": 0.13932693237438798,
    "train_transition": 0.05642815452301875,
    "train_dag": 0.0,
    "train_contrastive": 0.0,
    "val_total": 0.14334631924118316,
    "val_recon": 0.12564017091478621,
    "dag_constraint": 0.0,
    "time_s": 0.254730224609375
  },
  {
    "epoch": 2,
    "train_total": 0.14858220261521637,
    "train_recon": 0.1335528704803437,
    "train_transition": 0.015029330388642848,
    "train_dag": 0.0,
    "train_contrastive": 0.0,
    "val_total": 0.13324971816369466,
    "val_recon": 0.12285930131162916,
    "dag_constraint": 0.0,
    "time_s": 0.24716687202453613
  },
  {
    "epoch": 3,
    "train_total": 0.14087968016974628,
    "train_recon": 0.13053752109408379,
    "train_transition": 0.01034215881372802,
    "train_dag": 0.0,
    "train_contrastive": 0.0,
    "val_total": 0.1267483734658786,
    "val_recon": 0.11841129724468503,
    "dag_constraint": 0.0,
    "time_s": 0.24692130088806152
  },
  {
    "epoch": 4,
    "train_total": 0.1341384411789477,
    "train_recon": 0.12527019437402487,
    "train_transition": 0.008868247619830072,
    "train_dag": 0.0,
    "train_contrastive": 0.0,
    "val_total": 0.12089516328913825,
    "val_recon": 0.11285893086876188,
    "dag_constraint": 0.0,
    "time_s": 0.24573230743408203
  },
  {
    "epoch": 5,
    "train_total": 0.12705891230143607,
    "train_recon": 0.1182702851947397,
    "train_transition": 0.00878862728131935,
    "train_dag": 0.0,
    "train_contrastive": 0.0,
    "val_total": 0.11430081618683678,
    "val_recon": 0.10592945452247347,
    "dag_constraint": 0.0,
    "time_s": 0.24574971199035645
  },
  {
    "epoch": 6,
    "train_total": 0.12090428988449275,
    "train_recon": 0.11168977455236018,
    "train_transition": 0.00921451547765173,
    "train_dag": 0.0,
    "train_contrastive": 0.0,
    "val_total": 0.10801152352775846,
    "val_recon": 0.09935533255338669,
    "dag_constraint": 0.0,
    "time_s": 0.24333715438842773
  },
  {
    "epoch": 7,
    "train_total": 0.11469862842932343,
    "train_recon": 0.10501790069974959,
    "train_transition": 0.009680727263912559,
    "train_dag": 0.0,
    "train_contrastive": 0.0,
    "val_total": 0.1025056540966034,
    "val_recon": 0.09335968324116298,
    "dag_constraint": 0.0,
    "time_s": 0.2555058002471924
  },
  {
    "epoch": 8,
    "train_total": 0.10885368497110903,
    "train_recon": 0.0989515115506947,
    "train_transition": 0.00990217353682965,
    "train_dag": 0.0,
    "train_contrastive": 0.0,
    "val_total": 0.09710025893790382,
    "val_recon": 0.08772574897323336,
    "dag_constraint": 0.0,
    "time_s": 0.25180673599243164
  },
  {
    "epoch": 9,
    "train_total": 0.10344594437628984,
    "train_recon": 0.09336510696448386,
    "train_transition": 0.010080837004352361,
    "train_dag": 0.0,
    "train_contrastive": 0.0,
    "val_total": 0.0930466428399086,
    "val_recon": 0.08352676246847425,
    "dag_constraint": 0.0,
    "time_s": 0.24511337280273438
  },
  {
    "epoch": 10,
    "train_total": 0.09815336018800735,
    "train_recon": 0.08777847047895193,
    "train_transition": 0.010374889825470746,
    "train_dag": 0.0,
    "train_contrastive": 0.0,
    "val_total": 0.08814362010785512,
    "val_recon": 0.07847670039960317,
    "dag_constraint": 0.0,
    "time_s": 0.24505329132080078
  },
  {
    "epoch": 11,
    "train_total": 0.09364030882716179,
    "train_recon": 0.08268316346220672,
    "train_transition": 0.010957145685097203,
    "train_dag": 0.0,
    "train_contrastive": 0.0,
    "val_total": 0.08412757515907288,
    "val_recon": 0.07418672155056681,
    "dag_constraint": 0.0,
    "time_s": 0.24066615104675293
  },
  {
    "epoch": 12,
    "train_total": 0.08929796400479972,
    "train_recon": 0.07840003562159836,
    "train_transition": 0.010897928179474548,
    "train_dag": 0.0,
    "train_contrastive": 0.0,
    "val_total": 0.08092397664274488,
    "val_recon": 0.07044973277619906,
    "dag_constraint": 0.0,
    "time_s": 0.24071669578552246
  },
  {
    "epoch": 13,
    "train_total": 0.08538232021965086,
    "train_recon": 0.07417561684269458,
    "train_transition": 0.011206703493371606,
    "train_dag": 0.0,
    "train_contrastive": 0.0,
    "val_total": 0.07730522538934435,
    "val_recon": 0.06690694657819611,
    "dag_constraint": 0.0,
    "time_s": 0.24222803115844727
  },
  {
    "epoch": 14,
    "train_total": 0.08180441218428314,
    "train_recon": 0.07065851904917508,
    "train_transition": 0.01114589351345785,
    "train_dag": 0.0,
    "train_contrastive": 0.0,
    "val_total": 0.07423946580716542,
    "val_recon": 0.06372364610433578,
    "dag_constraint": 0.0,
    "time_s": 0.24603891372680664
  },
  {
    "epoch": 15,
    "train_total": 0.07825985550880432,
    "train_recon": 0.06690435251221061,
    "train_transition": 0.011355503491358832,
    "train_dag": 0.0,
    "train_contrastive": 0.0,
    "val_total": 0.07040402878608022,
    "val_recon": 0.060794075684888024,
    "dag_constraint": 0.0,
    "time_s": 0.24680519104003906
  },
  {
    "epoch": 16,
    "train_total": 0.07421794417314231,
    "train_recon": 0.06341610557865351,
    "train_transition": 0.010801838885527104,
    "train_dag": 0.0,
    "train_contrastive": 0.0,
    "val_total": 0.06762254131691796,
    "val_recon": 0.057707932378564565,
    "dag_constraint": 0.0,
    "time_s": 0.25651097297668457
  },
  {
    "epoch": 17,
    "train_total": 0.07150922587607056,
    "train_recon": 0.060900087701156735,
    "train_transition": 0.010609138640575111,
    "train_dag": 0.0,
    "train_contrastive": 0.0,
    "val_total": 0.06491611791508538,
    "val_recon": 0.05553853565028736,
    "dag_constraint": 0.0,
    "time_s": 0.24849319458007812
  },
  {
    "epoch": 18,
    "train_total": 0.06952260050456971,
    "train_recon": 0.05918089090846479,
    "train_transition": 0.010341709246858954,
    "train_dag": 0.0,
    "train_contrastive": 0.0,
    "val_total": 0.06346130424312182,
    "val_recon": 0.05433232603328569,
    "dag_constraint": 0.0,
    "time_s": 0.24711823463439941
  },
  {
    "epoch": 19,
    "train_total": 0.06654228654224426,
    "train_recon": 0.056483715190552175,
    "train_transition": 0.010058570740511641,
    "train_dag": 0.0,
    "train_contrastive": 0.0,
    "val_total": 0.06096420224223818,
    "val_recon": 0.05226868178163256,
    "dag_constraint": 0.0,
    "time_s": 0.24531769752502441
  },
  {
    "epoch": 20,
    "train_total": 0.06538900046143681,
    "train_recon": 0.05561749578919262,
    "train_transition": 0.009771504992386326,
    "train_dag": 0.0,
    "train_contrastive": 0.0,
    "val_total": 0.059339581323521476,
    "val_recon": 0.0507357157766819,
    "dag_constraint": 0.0,
    "time_s": 0.24906587600708008
  },
  {
    "epoch": 21,
    "train_total": 0.06298669544048607,
    "train_recon": 0.053629171452485025,
    "train_transition": 0.0093575241335202,
    "train_dag": 0.0,
    "train_contrastive": 0.0,
    "val_total": 0.0588207697229726,
    "val_recon": 0.050331001835209985,
    "dag_constraint": 0.0,
    "time_s": 0.2445225715637207
  },
  {
    "epoch": 22,
    "train_total": 0.0617538777878508,
    "train_recon": 0.05251429963391274,
    "train_transition": 0.009239578153938055,
    "train_dag": 0.0,
    "train_contrastive": 0.0,
    "val_total": 0.05740646964737347,
    "val_recon": 0.049241642866815837,
    "dag_constraint": 0.0,
    "time_s": 0.2460336685180664
  },
  {
    "epoch": 23,
    "train_total": 0.06052969046868384,
    "train_recon": 0.05177568504586816,
    "train_transition": 0.008754004811635241,
    "train_dag": 0.0,
    "train_contrastive": 0.0,
    "val_total": 0.05569613831383841,
    "val_recon": 0.04789131773369653,
    "dag_constraint": 0.0,
    "time_s": 0.24494481086730957
  },
  {
    "epoch": 24,
    "train_total": 0.05930771853309125,
    "train_recon": 0.05079918645787984,
    "train_transition": 0.00850853233714588,
    "train_dag": 0.0,
    "train_contrastive": 0.0,
    "val_total": 0.05752350123865264,
    "val_recon": 0.04937192052602768,
    "dag_constraint": 0.0,
    "time_s": 0.24676942825317383
  },
  {
    "epoch": 25,
    "train_total": 0.05921169591601938,
    "train_recon": 0.05092921806499362,
    "train_transition": 0.008282478258479387,
    "train_dag": 0.0,
    "train_contrastive": 0.0,
    "val_total": 0.055193589734179635,
    "val_recon": 0.04760567098855972,
    "dag_constraint": 0.0,
    "time_s": 0.24466371536254883
  },
  {
    "epoch": 26,
    "train_total": 0.057932399678975344,
    "train_recon": 0.04984025354497135,
    "train_transition": 0.008092146497801878,
    "train_dag": 0.0,
    "train_contrastive": 0.0,
    "val_total": 0.0538896524480411,
    "val_recon": 0.04674253772412028,
    "dag_constraint": 0.0,
    "time_s": 0.2487185001373291
  },
  {
    "epoch": 27,
    "train_total": 0.057288698153570294,
    "train_recon": 0.049569322844035923,
    "train_transition": 0.007719375076703727,
    "train_dag": 0.0,
    "train_contrastive": 0.0,
    "val_total": 0.052874318190983365,
    "val_recon": 0.045935578112091334,
    "dag_constraint": 0.0,
    "time_s": 0.2459554672241211
  },
  {
    "epoch": 28,
    "train_total": 0.056322987889871,
    "train_recon": 0.048717718687839806,
    "train_transition": 0.007605269231135026,
    "train_dag": 0.0,
    "train_contrastive": 0.0,
    "val_total": 0.052683546606983454,
    "val_recon": 0.04599436691829136,
    "dag_constraint": 0.0,
    "time_s": 0.25252866744995117
  },
  {
    "epoch": 29,
    "train_total": 0.05522191466297954,
    "train_recon": 0.047922843717969954,
    "train_transition": 0.007299071177840233,
    "train_dag": 0.0,
    "train_contrastive": 0.0,
    "val_total": 0.051557215728930066,
    "val_recon": 0.045213116598980765,
    "dag_constraint": 0.0,
    "time_s": 0.2471153736114502
  },
  {
    "epoch": 30,
    "train_total": 0.05476307577919215,
    "train_recon": 0.04763771430589259,
    "train_transition": 0.007125361371436156,
    "train_dag": 0.0,
    "train_contrastive": 0.0,
    "val_total": 0.051698245108127594,
    "val_recon": 0.04562465261135783,
    "dag_constraint": 0.0,
    "time_s": 0.25182199478149414
  },
  {
    "epoch": 31,
    "train_total": 0.05413899524137378,
    "train_recon": 0.047274150187149644,
    "train_transition": 0.006864845257950947,
    "train_dag": 0.0,
    "train_contrastive": 0.0,
    "val_total": 0.05121119959013803,
    "val_recon": 0.04479409594620977,
    "dag_constraint": 0.0,
    "time_s": 0.2467958927154541
  },
  {
    "epoch": 32,
    "train_total": 0.05386305879801512,
    "train_recon": 0.046944343601353467,
    "train_transition": 0.006918715385836549,
    "train_dag": 0.0,
    "train_contrastive": 0.0,
    "val_total": 0.050429304263421466,
    "val_recon": 0.04444562430892672,
    "dag_constraint": 0.0,
    "time_s": 0.2470107078552246
  },
  {
    "epoch": 33,
    "train_total": 0.0533743379637599,
    "train_recon": 0.04654184356331825,
    "train_transition": 0.006832494676928036,
    "train_dag": 0.0,
    "train_contrastive": 0.0,
    "val_total": 0.0491498809839998,
    "val_recon": 0.04346883829150881,
    "dag_constraint": 0.0,
    "time_s": 0.2458648681640625
  },
  {
    "epoch": 34,
    "train_total": 0.05267208768054843,
    "train_recon": 0.04604936356190592,
    "train_transition": 0.006622723682085052,
    "train_dag": 0.0,
    "train_contrastive": 0.0,
    "val_total": 0.049612736595528464,
    "val_recon": 0.043585230729409626,
    "dag_constraint": 0.0,
    "time_s": 0.2442939281463623
  },
  {
    "epoch": 35,
    "train_total": 0.05291027668863535,
    "train_recon": 0.046323876711539924,
    "train_transition": 0.006586400137166493,
    "train_dag": 0.0,
    "train_contrastive": 0.0,
    "val_total": 0.04935312856520925,
    "val_recon": 0.04343376149024282,
    "dag_constraint": 0.0,
    "time_s": 0.24588394165039062
  },
  {
    "epoch": 36,
    "train_total": 0.05244664091151208,
    "train_recon": 0.045765464077703655,
    "train_transition": 0.006681176892016083,
    "train_dag": 0.0,
    "train_contrastive": 0.0,
    "val_total": 0.04964394015925271,
    "val_recon": 0.04382172439779554,
    "dag_constraint": 0.0,
    "time_s": 0.24863600730895996
  },
  {
    "epoch": 37,
    "train_total": 0.051462923060171306,
    "train_recon": 0.04475881124380976,
    "train_transition": 0.006704111729050055,
    "train_dag": 0.0,
    "train_contrastive": 0.0,
    "val_total": 0.04898084221141679,
    "val_recon": 0.043003473430871964,
    "dag_constraint": 0.0,
    "time_s": 0.24555444717407227
  },
  {
    "epoch": 38,
    "train_total": 0.05083191895391792,
    "train_recon": 0.04422685503959656,
    "train_transition": 0.006605064001632854,
    "train_dag": 0.0,
    "train_contrastive": 0.0,
    "val_total": 0.04787645222885268,
    "val_recon": 0.04219833814672062,
    "dag_constraint": 0.0,
    "time_s": 0.2454376220703125
  },
  {
    "epoch": 39,
    "train_total": 0.05026427935808897,
    "train_recon": 0.043743730057030916,
    "train_transition": 0.006520549213746563,
    "train_dag": 0.0,
    "train_contrastive": 0.0,
    "val_total": 0.04800707953316825,
    "val_recon": 0.04236140687550817,
    "dag_constraint": 0.0,
    "time_s": 0.24663043022155762
  },
  {
    "epoch": 40,
    "train_total": 0.049700685194693506,
    "train_recon": 0.043038940289989114,
    "train_transition": 0.006661744628218003,
    "train_dag": 0.0,
    "train_contrastive": 0.0,
    "val_total": 0.04663585019963128,
    "val_recon": 0.04086920991539955,
    "dag_constraint": 0.0,
    "time_s": 0.24689936637878418
  },
  {
    "epoch": 41,
    "train_total": 0.04950688360258937,
    "train_recon": 0.042895566672086716,
    "train_transition": 0.006611317046917975,
    "train_dag": 0.0,
    "train_contrastive": 0.0,
    "val_total": 0.04603379698736327,
    "val_recon": 0.04052331245371273,
    "dag_constraint": 0.0,
    "time_s": 0.24787425994873047
  },
  {
    "epoch": 42,
    "train_total": 0.048671626253053546,
    "train_recon": 0.04203551076352596,
    "train_transition": 0.006636115125729702,
    "train_dag": 0.0,
    "train_contrastive": 0.0,
    "val_total": 0.045759807739939005,
    "val_recon": 0.04008764826825687,
    "dag_constraint": 0.0,
    "time_s": 0.24867653846740723
  },
  {
    "epoch": 43,
    "train_total": 0.04848978447262198,
    "train_recon": 0.041909337509423494,
    "train_transition": 0.00658044675947167,
    "train_dag": 0.0,
    "train_contrastive": 0.0,
    "val_total": 0.04515533894300461,
    "val_recon": 0.03951193339058331,
    "dag_constraint": 0.0,
    "time_s": 0.24460077285766602
  },
  {
    "epoch": 44,
    "train_total": 0.04767159069888294,
    "train_recon": 0.04108658421318978,
    "train_transition": 0.006585006616660394,
    "train_dag": 0.0,
    "train_contrastive": 0.0,
    "val_total": 0.04587578134877341,
    "val_recon": 0.04017054023487227,
    "dag_constraint": 0.0,
    "time_s": 0.251340389251709
  },
  {
    "epoch": 45,
    "train_total": 0.047338879900053144,
    "train_recon": 0.040891977841965854,
    "train_transition": 0.006446902407333255,
    "train_dag": 0.0,
    "train_contrastive": 0.0,
    "val_total": 0.04618106409907341,
    "val_recon": 0.04038442937391145,
    "dag_constraint": 0.0,
    "time_s": 0.24596619606018066
  },
  {
    "epoch": 46,
    "train_total": 0.04674785304814577,
    "train_recon": 0.04028408683370799,
    "train_transition": 0.006463766127126291,
    "train_dag": 0.0,
    "train_contrastive": 0.0,
    "val_total": 0.044288351599659236,
    "val_recon": 0.03888818249106407,
    "dag_constraint": 0.0,
    "time_s": 0.2501394748687744
  },
  {
    "epoch": 47,
    "train_total": 0.04642597516067326,
    "train_recon": 0.04008534038439393,
    "train_transition": 0.006340635009109974,
    "train_dag": 0.0,
    "train_contrastive": 0.0,
    "val_total": 0.046373741435153146,
    "val_recon": 0.041059711149760654,
    "dag_constraint": 0.0,
    "time_s": 0.2530813217163086
  },
  {
    "epoch": 48,
    "train_total": 0.04587780951987952,
    "train_recon": 0.03971151832956821,
    "train_transition": 0.006166291248518974,
    "train_dag": 0.0,
    "train_contrastive": 0.0,
    "val_total": 0.044562588312796185,
    "val_recon": 0.039267439395189285,
    "dag_constraint": 0.0,
    "time_s": 0.2630152702331543
  },
  {
    "epoch": 49,
    "train_total": 0.04516410571523011,
    "train_recon": 0.039117590873502195,
    "train_transition": 0.006046514856279828,
    "train_dag": 0.0,
    "train_contrastive": 0.0,
    "val_total": 0.04330505643572126,
    "val_recon": 0.03823572450450489,
    "dag_constraint": 0.0,
    "time_s": 0.257993221282959
  },
  {
    "epoch": 50,
    "train_total": 0.045433228951878846,
    "train_recon": 0.03943561506457627,
    "train_transition": 0.005997613799991086,
    "train_dag": 0.0,
    "train_contrastive": 0.0,
    "val_total": 0.04323472348707063,
    "val_recon": 0.03830690096531596,
    "dag_constraint": 0.0,
    "time_s": 0.25399351119995117
  },
  {
    "epoch": 51,
    "train_total": 0.04443608887959272,
    "train_recon": 0.038672505179420114,
    "train_transition": 0.005763584049418569,
    "train_dag": 0.0,
    "train_contrastive": 0.0,
    "val_total": 0.04270093462296894,
    "val_recon": 0.037754936409848075,
    "dag_constraint": 0.0,
    "time_s": 0.26138854026794434
  },
  {
    "epoch": 52,
    "train_total": 0.044388737296685576,
    "train_recon": 0.03866462339647114,
    "train_transition": 0.005724114162148908,
    "train_dag": 0.0,
    "train_contrastive": 0.0,
    "val_total": 0.04218229012829917,
    "val_recon": 0.03732876905373165,
    "dag_constraint": 0.0,
    "time_s": 0.25324201583862305
  },
  {
    "epoch": 53,
    "train_total": 0.04428565804846585,
    "train_recon": 0.03862571471836418,
    "train_transition": 0.0056599431845825166,
    "train_dag": 0.0,
    "train_contrastive": 0.0,
    "val_total": 0.043075857417924066,
    "val_recon": 0.03834144930754389,
    "dag_constraint": 0.0,
    "time_s": 0.24742937088012695
  },
  {
    "epoch": 54,
    "train_total": 0.04406264121644199,
    "train_recon": 0.03848737117368728,
    "train_transition": 0.005575270115514286,
    "train_dag": 0.0,
    "train_contrastive": 0.0,
    "val_total": 0.04282914261732783,
    "val_recon": 0.038171726145914624,
    "dag_constraint": 0.0,
    "time_s": 0.24508929252624512
  },
  {
    "epoch": 55,
    "train_total": 0.04338850220665336,
    "train_recon": 0.03793882968602702,
    "train_transition": 0.005449672680697404,
    "train_dag": 0.0,
    "train_contrastive": 0.0,
    "val_total": 0.041598449860300334,
    "val_recon": 0.03674185329249927,
    "dag_constraint": 0.0,
    "time_s": 0.24819493293762207
  },
  {
    "epoch": 56,
    "train_total": 0.042640987085178494,
    "train_recon": 0.037242884980514646,
    "train_transition": 0.0053981021483195946,
    "train_dag": 0.0,
    "train_contrastive": 0.0,
    "val_total": 0.04128759194697652,
    "val_recon": 0.03671123459935188,
    "dag_constraint": 0.0,
    "time_s": 0.2564971446990967
  },
  {
    "epoch": 57,
    "train_total": 0.042867636773735285,
    "train_recon": 0.037584328558295965,
    "train_transition": 0.005283308259095065,
    "train_dag": 0.0,
    "train_contrastive": 0.0,
    "val_total": 0.04164408892393112,
    "val_recon": 0.03707056439348629,
    "dag_constraint": 0.0,
    "time_s": 0.2538776397705078
  },
  {
    "epoch": 58,
    "train_total": 0.04250150907319039,
    "train_recon": 0.037308176630176604,
    "train_transition": 0.005193332108319737,
    "train_dag": 0.0,
    "train_contrastive": 0.0,
    "val_total": 0.04128282570413181,
    "val_recon": 0.03682821882622583,
    "dag_constraint": 0.0,
    "time_s": 0.2478504180908203
  },
  {
    "epoch": 59,
    "train_total": 0.04245847859419882,
    "train_recon": 0.037330193794332445,
    "train_transition": 0.0051282846834510565,
    "train_dag": 0.0,
    "train_contrastive": 0.0,
    "val_total": 0.04112774772303445,
    "val_recon": 0.036636942731482644,
    "dag_constraint": 0.0,
    "time_s": 0.24338531494140625
  },
  {
    "epoch": 60,
    "train_total": 0.04153215291444212,
    "train_recon": 0.03633486421313137,
    "train_transition": 0.005197288512135856,
    "train_dag": 0.0,
    "train_contrastive": 0.0,
    "val_total": 0.040634230843612125,
    "val_recon": 0.0361736390207495,
    "dag_constraint": 0.0,
    "time_s": 0.24640417098999023
  },
  {
    "epoch": 61,
    "train_total": 0.04178138158749789,
    "train_recon": 0.036701052566058934,
    "train_transition": 0.005080328541225754,
    "train_dag": 0.0,
    "train_contrastive": 0.0,
    "val_total": 0.04067898860999516,
    "val_recon": 0.036067698150873184,
    "dag_constraint": 0.0,
    "time_s": 0.2524905204772949
  },
  {
    "epoch": 62,
    "train_total": 0.040872872807085514,
    "train_recon": 0.03574976650997996,
    "train_transition": 0.005123106166138314,
    "train_dag": 0.0,
    "train_contrastive": 0.0,
    "val_total": 0.03915686958602497,
    "val_recon": 0.03475436355386462,
    "dag_constraint": 0.0,
    "time_s": 0.24768948554992676
  },
  {
    "epoch": 63,
    "train_total": 0.040924368891865015,
    "train_recon": 0.035760413797106594,
    "train_transition": 0.005163955109310336,
    "train_dag": 0.0,
    "train_contrastive": 0.0,
    "val_total": 0.04258788536701884,
    "val_recon": 0.03800399122493608,
    "dag_constraint": 0.0,
    "time_s": 0.24956655502319336
  },
  {
    "epoch": 64,
    "train_total": 0.0402545373653993,
    "train_recon": 0.03503620100673288,
    "train_transition": 0.005218336504185572,
    "train_dag": 0.0,
    "train_contrastive": 0.0,
    "val_total": 0.039135996784482686,
    "val_recon": 0.034541905990668705,
    "dag_constraint": 0.0,
    "time_s": 0.2517092227935791
  },
  {
    "epoch": 65,
    "train_total": 0.03970933996606618,
    "train_recon": 0.03450972615974024,
    "train_transition": 0.0051996139518450946,
    "train_dag": 0.0,
    "train_contrastive": 0.0,
    "val_total": 0.03970359904425485,
    "val_recon": 0.03527580787028585,
    "dag_constraint": 0.0,
    "time_s": 0.25080037117004395
  },
  {
    "epoch": 66,
    "train_total": 0.04018282622564584,
    "train_recon": 0.034975343907717615,
    "train_transition": 0.005207482434343547,
    "train_dag": 0.0,
    "train_contrastive": 0.0,
    "val_total": 0.038933096187455316,
    "val_recon": 0.034338969737291336,
    "dag_constraint": 0.0,
    "time_s": 0.2537250518798828
  },
  {
    "epoch": 67,
    "train_total": 0.03936379647348076,
    "train_recon": 0.03411934745963663,
    "train_transition": 0.005244449042947963,
    "train_dag": 0.0,
    "train_contrastive": 0.0,
    "val_total": 0.03820594559822764,
    "val_recon": 0.03357127468500819,
    "dag_constraint": 0.0,
    "time_s": 0.24486446380615234
  },
  {
    "epoch": 68,
    "train_total": 0.03824953315779567,
    "train_recon": 0.03295009850990027,
    "train_transition": 0.0052994345023762435,
    "train_dag": 0.0,
    "train_contrastive": 0.0,
    "val_total": 0.038501906607832224,
    "val_recon": 0.03362549761576312,
    "dag_constraint": 0.0,
    "time_s": 0.24756240844726562
  },
  {
    "epoch": 69,
    "train_total": 0.03810574521776289,
    "train_recon": 0.032793916820082814,
    "train_transition": 0.005311828848789446,
    "train_dag": 0.0,
    "train_contrastive": 0.0,
    "val_total": 0.03742143086024693,
    "val_recon": 0.03275763749011925,
    "dag_constraint": 0.0,
    "time_s": 0.2517359256744385
  },
  {
    "epoch": 70,
    "train_total": 0.03821713849902153,
    "train_recon": 0.03288102790247649,
    "train_transition": 0.005336110756616108,
    "train_dag": 0.0,
    "train_contrastive": 0.0,
    "val_total": 0.03769565799406597,
    "val_recon": 0.03301622612135751,
    "dag_constraint": 0.0,
    "time_s": 0.24938631057739258
  },
  {
    "epoch": 71,
    "train_total": 0.03802994452416897,
    "train_recon": 0.032734024338424206,
    "train_transition": 0.005295920564094558,
    "train_dag": 0.0,
    "train_contrastive": 0.0,
    "val_total": 0.03784661420754024,
    "val_recon": 0.032995683274098804,
    "dag_constraint": 0.0,
    "time_s": 0.24651217460632324
  },
  {
    "epoch": 72,
    "train_total": 0.03741591819562018,
    "train_recon": 0.03214253333862871,
    "train_transition": 0.005273384464089759,
    "train_dag": 0.0,
    "train_contrastive": 0.0,
    "val_total": 0.03708717333418982,
    "val_recon": 0.03231985920241901,
    "dag_constraint": 0.0,
    "time_s": 0.24934101104736328
  },
  {
    "epoch": 73,
    "train_total": 0.037007402745075524,
    "train_recon": 0.03173223859630525,
    "train_transition": 0.005275164192426018,
    "train_dag": 0.0,
    "train_contrastive": 0.0,
    "val_total": 0.03581249767116138,
    "val_recon": 0.03114965371787548,
    "dag_constraint": 0.0,
    "time_s": 0.24638581275939941
  },
  {
    "epoch": 74,
    "train_total": 0.03651270363479853,
    "train_recon": 0.03133439342491329,
    "train_transition": 0.005178310326300561,
    "train_dag": 0.0,
    "train_contrastive": 0.0,
    "val_total": 0.035277088837964196,
    "val_recon": 0.030678422057202885,
    "dag_constraint": 0.0,
    "time_s": 0.24889707565307617
  },
  {
    "epoch": 75,
    "train_total": 0.03665464324876666,
    "train_recon": 0.031513960973825306,
    "train_transition": 0.005140682187629864,
    "train_dag": 0.0,
    "train_contrastive": 0.0,
    "val_total": 0.03529530391097069,
    "val_recon": 0.030765128188899586,
    "dag_constraint": 0.0,
    "time_s": 0.2487325668334961
  },
  {
    "epoch": 76,
    "train_total": 0.03587407316081226,
    "train_recon": 0.030795190134085715,
    "train_transition": 0.005078883230453357,
    "train_dag": 0.0,
    "train_contrastive": 0.0,
    "val_total": 0.03576342814735004,
    "val_recon": 0.03138584936303752,
    "dag_constraint": 0.0,
    "time_s": 0.25555944442749023
  },
  {
    "epoch": 77,
    "train_total": 0.035710862022824585,
    "train_recon": 0.030726901022717357,
    "train_transition": 0.004983960883691907,
    "train_dag": 0.0,
    "train_contrastive": 0.0,
    "val_total": 0.03474684911114829,
    "val_recon": 0.030342324503830502,
    "dag_constraint": 0.0,
    "time_s": 0.25115394592285156
  },
  {
    "epoch": 78,
    "train_total": 0.035145982808899134,
    "train_recon": 0.030238599400036037,
    "train_transition": 0.004907383306999691,
    "train_dag": 0.0,
    "train_contrastive": 0.0,
    "val_total": 0.035594893885510306,
    "val_recon": 0.03126720551933561,
    "dag_constraint": 0.0,
    "time_s": 0.2512507438659668
  },
  {
    "epoch": 79,
    "train_total": 0.03545220720116049,
    "train_recon": 0.030633665388450027,
    "train_transition": 0.004818541754502803,
    "train_dag": 0.0,
    "train_contrastive": 0.0,
    "val_total": 0.03537014605743544,
    "val_recon": 0.03107200376689434,
    "dag_constraint": 0.0,
    "time_s": 0.2490527629852295
  },
  {
    "epoch": 80,
    "train_total": 0.035240198543760926,
    "train_recon": 0.03041386033874005,
    "train_transition": 0.004826338088605553,
    "train_dag": 0.0,
    "train_contrastive": 0.0,
    "val_total": 0.034037520842892785,
    "val_recon": 0.0298214749033962,
    "dag_constraint": 0.0,
    "time_s": 0.2505640983581543
  },
  {
    "epoch": 81,
    "train_total": 0.03481922158971429,
    "train_recon": 0.030018343299161643,
    "train_transition": 0.004800878377864137,
    "train_dag": 0.0,
    "train_contrastive": 0.0,
    "val_total": 0.03477745556405613,
    "val_recon": 0.030707029093589102,
    "dag_constraint": 0.0,
    "time_s": 0.24907660484313965
  },
  {
    "epoch": 82,
    "train_total": 0.035009255982004106,
    "train_recon": 0.03041848837165162,
    "train_transition": 0.004590767726767808,
    "train_dag": 0.0,
    "train_contrastive": 0.0,
    "val_total": 0.034945442740406306,
    "val_recon": 0.030969406611153057,
    "dag_constraint": 0.0,
    "time_s": 0.2511329650878906
  },
  {
    "epoch": 83,
    "train_total": 0.034262772591318935,
    "train_recon": 0.029687118076253682,
    "train_transition": 0.0045756548788631335,
    "train_dag": 0.0,
    "train_contrastive": 0.0,
    "val_total": 0.03419361902134759,
    "val_recon": 0.03018455845969064,
    "dag_constraint": 0.0,
    "time_s": 0.24763798713684082
  },
  {
    "epoch": 84,
    "train_total": 0.03391127404756844,
    "train_recon": 0.029409313341602683,
    "train_transition": 0.004501960866036825,
    "train_dag": 0.0,
    "train_contrastive": 0.0,
    "val_total": 0.03373421888266291,
    "val_recon": 0.029836455093962804,
    "dag_constraint": 0.0,
    "time_s": 0.2571592330932617
  },
  {
    "epoch": 85,
    "train_total": 0.03417256590910256,
    "train_recon": 0.029791664506774396,
    "train_transition": 0.0043809016642626375,
    "train_dag": 0.0,
    "train_contrastive": 0.0,
    "val_total": 0.033237600166882784,
    "val_recon": 0.029326964435832843,
    "dag_constraint": 0.0,
    "time_s": 0.2528383731842041
  },
  {
    "epoch": 86,
    "train_total": 0.034069666697178036,
    "train_recon": 0.029705503140576184,
    "train_transition": 0.004364163687569089,
    "train_dag": 0.0,
    "train_contrastive": 0.0,
    "val_total": 0.034641169543777196,
    "val_recon": 0.03079146146774292,
    "dag_constraint": 0.0,
    "time_s": 0.25215578079223633
  },
  {
    "epoch": 87,
    "train_total": 0.033772245107684284,
    "train_recon": 0.02947608637623489,
    "train_transition": 0.004296158876968548,
    "train_dag": 0.0,
    "train_contrastive": 0.0,
    "val_total": 0.033533648188625066,
    "val_recon": 0.029843075733099664,
    "dag_constraint": 0.0,
    "time_s": 0.2589728832244873
  },
  {
    "epoch": 88,
    "train_total": 0.03377915557939559,
    "train_recon": 0.029574058658909053,
    "train_transition": 0.004205096905934624,
    "train_dag": 0.0,
    "train_contrastive": 0.0,
    "val_total": 0.033478857683283944,
    "val_recon": 0.029807748273015022,
    "dag_constraint": 0.0,
    "time_s": 0.25528836250305176
  },
  {
    "epoch": 89,
    "train_total": 0.03418533323565498,
    "train_recon": 0.030012157862074673,
    "train_transition": 0.004173175140749663,
    "train_dag": 0.0,
    "train_contrastive": 0.0,
    "val_total": 0.03341413715056011,
    "val_recon": 0.029630787670612335,
    "dag_constraint": 0.0,
    "time_s": 0.2541797161102295
  },
  {
    "epoch": 90,
    "train_total": 0.03438811574596912,
    "train_recon": 0.030168088560458273,
    "train_transition": 0.004220026850816794,
    "train_dag": 0.0,
    "train_contrastive": 0.0,
    "val_total": 0.03390427944915635,
    "val_recon": 0.03022287493305547,
    "dag_constraint": 0.0,
    "time_s": 0.2526071071624756
  },
  {
    "epoch": 91,
    "train_total": 0.03363196464488283,
    "train_recon": 0.02954147575655952,
    "train_transition": 0.004090488699148409,
    "train_dag": 0.0,
    "train_contrastive": 0.0,
    "val_total": 0.03391159006527492,
    "val_recon": 0.030248319464070455,
    "dag_constraint": 0.0,
    "time_s": 0.25432324409484863
  },
  {
    "epoch": 92,
    "train_total": 0.03361890942323953,
    "train_recon": 0.029586880758870393,
    "train_transition": 0.00403202859160956,
    "train_dag": 0.0,
    "train_contrastive": 0.0,
    "val_total": 0.03467802277633122,
    "val_recon": 0.03101943646158491,
    "dag_constraint": 0.0,
    "time_s": 0.25344109535217285
  },
  {
    "epoch": 93,
    "train_total": 0.033552042848896235,
    "train_recon": 0.029529942316003144,
    "train_transition": 0.0040221004455816,
    "train_dag": 0.0,
    "train_contrastive": 0.0,
    "val_total": 0.03325890696474484,
    "val_recon": 0.02972446195781231,
    "dag_constraint": 0.0,
    "time_s": 0.2519047260284424
  },
  {
    "epoch": 94,
    "train_total": 0.03328225715085864,
    "train_recon": 0.029341983783524483,
    "train_transition": 0.00394027354195714,
    "train_dag": 0.0,
    "train_contrastive": 0.0,
    "val_total": 0.03296221313732011,
    "val_recon": 0.029495501092502048,
    "dag_constraint": 0.0,
    "time_s": 0.2520763874053955
  },
  {
    "epoch": 95,
    "train_total": 0.033926161006093025,
    "train_recon": 0.030007043620571494,
    "train_transition": 0.003919117050827481,
    "train_dag": 0.0,
    "train_contrastive": 0.0,
    "val_total": 0.03274304419755936,
    "val_recon": 0.029293198404567584,
    "dag_constraint": 0.0,
    "time_s": 0.24830889701843262
  },
  {
    "epoch": 96,
    "train_total": 0.03325564198894426,
    "train_recon": 0.029325434297788888,
    "train_transition": 0.0039302075892919675,
    "train_dag": 0.0,
    "train_contrastive": 0.0,
    "val_total": 0.032577529549598694,
    "val_recon": 0.029253090332661356,
    "dag_constraint": 0.0,
    "time_s": 0.25502443313598633
  },
  {
    "epoch": 97,
    "train_total": 0.033166482811793685,
    "train_recon": 0.029347293369937688,
    "train_transition": 0.0038191898493096232,
    "train_dag": 0.0,
    "train_contrastive": 0.0,
    "val_total": 0.03379437327384949,
    "val_recon": 0.030342699959874153,
    "dag_constraint": 0.0,
    "time_s": 0.25400495529174805
  },
  {
    "epoch": 98,
    "train_total": 0.033143393869977444,
    "train_recon": 0.029351597651839256,
    "train_transition": 0.0037917962326901034,
    "train_dag": 0.0,
    "train_contrastive": 0.0,
    "val_total": 0.03355130021061216,
    "val_recon": 0.030197801866701672,
    "dag_constraint": 0.0,
    "time_s": 0.2519683837890625
  },
  {
    "epoch": 99,
    "train_total": 0.03285509266424924,
    "train_recon": 0.029153381707146764,
    "train_transition": 0.0037017106951680034,
    "train_dag": 0.0,
    "train_contrastive": 0.0,
    "val_total": 0.032308447041681836,
    "val_recon": 0.02893005684018135,
    "dag_constraint": 0.0,
    "time_s": 0.2516055107116699
  },
  {
    "epoch": 100,
    "train_total": 0.0326886466355063,
    "train_recon": 0.028965564037207514,
    "train_transition": 0.003723082860233262,
    "train_dag": 0.0,
    "train_contrastive": 0.0,
    "val_total": 0.03241248694913728,
    "val_recon": 0.029104450717568398,
    "dag_constraint": 0.0,
    "time_s": 0.2502737045288086
  },
  {
    "epoch": 101,
    "train_total": 0.03264088154537603,
    "train_recon": 0.02899608574807644,
    "train_transition": 0.0036447957390919328,
    "train_dag": 0.0,
    "train_contrastive": 0.0,
    "val_total": 0.03195037932268211,
    "val_recon": 0.028716398935232843,
    "dag_constraint": 0.0,
    "time_s": 0.25084996223449707
  },
  {
    "epoch": 102,
    "train_total": 0.03272185690002516,
    "train_recon": 0.02904708980349824,
    "train_transition": 0.003674767169286497,
    "train_dag": 0.0,
    "train_contrastive": 0.0,
    "val_total": 0.03278477782649653,
    "val_recon": 0.029621211545807973,
    "dag_constraint": 0.0,
    "time_s": 0.2518291473388672
  },
  {
    "epoch": 103,
    "train_total": 0.033020585717167705,
    "train_recon": 0.02942102262750268,
    "train_transition": 0.003599563264288008,
    "train_dag": 0.0,
    "train_contrastive": 0.0,
    "val_total": 0.03196640419108527,
    "val_recon": 0.028832524216600826,
    "dag_constraint": 0.0,
    "time_s": 0.24992656707763672
  },
  {
    "epoch": 104,
    "train_total": 0.03260943409986794,
    "train_recon": 0.029092773736920208,
    "train_transition": 0.0035166603774996474,
    "train_dag": 0.0,
    "train_contrastive": 0.0,
    "val_total": 0.03287135889487607,
    "val_recon": 0.029657404071518352,
    "dag_constraint": 0.0,
    "time_s": 0.24975347518920898
  },
  {
    "epoch": 105,
    "train_total": 0.03259188070660457,
    "train_recon": 0.028997984249144793,
    "train_transition": 0.0035938965156674385,
    "train_dag": 0.0,
    "train_contrastive": 0.0,
    "val_total": 0.03286337400121348,
    "val_recon": 0.029653738385864666,
    "dag_constraint": 0.0,
    "time_s": 0.25086474418640137
  },
  {
    "epoch": 106,
    "train_total": 0.03218221623683348,
    "train_recon": 0.028692715102806687,
    "train_transition": 0.003489501148578711,
    "train_dag": 0.0,
    "train_contrastive": 0.0,
    "val_total": 0.03200161749763148,
    "val_recon": 0.028864624510918344,
    "dag_constraint": 0.0,
    "time_s": 0.254101037979126
  },
  {
    "epoch": 107,
    "train_total": 0.03222547110635787,
    "train_recon": 0.02872959600063041,
    "train_transition": 0.0034958750184159726,
    "train_dag": 0.0,
    "train_contrastive": 0.0,
    "val_total": 0.03209336155227253,
    "val_recon": 0.02896610221692494,
    "dag_constraint": 0.0,
    "time_s": 0.25182247161865234
  },
  {
    "epoch": 108,
    "train_total": 0.032423230120912194,
    "train_recon": 0.0290202833712101,
    "train_transition": 0.0034029468370135874,
    "train_dag": 0.0,
    "train_contrastive": 0.0,
    "val_total": 0.03260960376688412,
    "val_recon": 0.029521801908101355,
    "dag_constraint": 0.0,
    "time_s": 0.25295400619506836
  },
  {
    "epoch": 109,
    "train_total": 0.0324395663337782,
    "train_recon": 0.02899831987451762,
    "train_transition": 0.003441246459260583,
    "train_dag": 0.0,
    "train_contrastive": 0.0,
    "val_total": 0.03291996515222958,
    "val_recon": 0.02984246052801609,
    "dag_constraint": 0.0,
    "time_s": 0.2540395259857178
  },
  {
    "epoch": 110,
    "train_total": 0.0325835351832211,
    "train_recon": 0.02918877813499421,
    "train_transition": 0.003394757237401791,
    "train_dag": 0.0,
    "train_contrastive": 0.0,
    "val_total": 0.03285955211945942,
    "val_recon": 0.0297922638377973,
    "dag_constraint": 0.0,
    "time_s": 0.24721097946166992
  },
  {
    "epoch": 111,
    "train_total": 0.03291045699734241,
    "train_recon": 0.029496848001144826,
    "train_transition": 0.0034136088797822595,
    "train_dag": 0.0,
    "train_contrastive": 0.0,
    "val_total": 0.03259992173739842,
    "val_recon": 0.029555487845625197,
    "dag_constraint": 0.0,
    "time_s": 0.2446727752685547
  },
  {
    "epoch": 112,
    "train_total": 0.03212624927982688,
    "train_recon": 0.028805624169763178,
    "train_transition": 0.003320625371998176,
    "train_dag": 0.0,
    "train_contrastive": 0.0,
    "val_total": 0.031786322593688965,
    "val_recon": 0.028755046693342074,
    "dag_constraint": 0.0,
    "time_s": 0.24856805801391602
  },
  {
    "epoch": 113,
    "train_total": 0.03236086282413453,
    "train_recon": 0.029015290609095246,
    "train_transition": 0.003345572084072046,
    "train_dag": 0.0,
    "train_contrastive": 0.0,
    "val_total": 0.03139265200921467,
    "val_recon": 0.02846312416451318,
    "dag_constraint": 0.0,
    "time_s": 0.24944210052490234
  },
  {
    "epoch": 114,
    "train_total": 0.031772114511113614,
    "train_recon": 0.02849096682621166,
    "train_transition": 0.003281147830421105,
    "train_dag": 0.0,
    "train_contrastive": 0.0,
    "val_total": 0.031255324238112996,
    "val_recon": 0.02842314062373979,
    "dag_constraint": 0.0,
    "time_s": 0.24997520446777344
  },
  {
    "epoch": 115,
    "train_total": 0.03184817294823006,
    "train_recon": 0.028620253433473408,
    "train_transition": 0.0032279196748277172,
    "train_dag": 0.0,
    "train_contrastive": 0.0,
    "val_total": 0.032756024439420016,
    "val_recon": 0.029760205053857396,
    "dag_constraint": 0.0,
    "time_s": 0.24623942375183105
  },
  {
    "epoch": 116,
    "train_total": 0.03186801355332136,
    "train_recon": 0.02859807212371379,
    "train_transition": 0.0032699414441594854,
    "train_dag": 0.0,
    "train_contrastive": 0.0,
    "val_total": 0.031125700899532864,
    "val_recon": 0.02828414791396686,
    "dag_constraint": 0.0,
    "time_s": 0.24967336654663086
  },
  {
    "epoch": 117,
    "train_total": 0.03241901710862294,
    "train_recon": 0.02919800259405747,
    "train_transition": 0.0032210147473961115,
    "train_dag": 0.0,
    "train_contrastive": 0.0,
    "val_total": 0.0326025089515107,
    "val_recon": 0.02973251257623945,
    "dag_constraint": 0.0,
    "time_s": 0.24693632125854492
  },
  {
    "epoch": 118,
    "train_total": 0.03243385849054903,
    "train_recon": 0.029257337388116866,
    "train_transition": 0.003176521116984077,
    "train_dag": 0.0,
    "train_contrastive": 0.0,
    "val_total": 0.03446865560753005,
    "val_recon": 0.03163287016962256,
    "dag_constraint": 0.0,
    "time_s": 0.25096869468688965
  },
  {
    "epoch": 119,
    "train_total": 0.03254780621500686,
    "train_recon": 0.029371061478741467,
    "train_transition": 0.0031767445761943236,
    "train_dag": 0.0,
    "train_contrastive": 0.0,
    "val_total": 0.03348109259137085,
    "val_recon": 0.030569433101585934,
    "dag_constraint": 0.0,
    "time_s": 0.24944067001342773
  },
  {
    "epoch": 120,
    "train_total": 0.03248656005598605,
    "train_recon": 0.0292990937596187,
    "train_transition": 0.0031874665583018214,
    "train_dag": 0.0,
    "train_contrastive": 0.0,
    "val_total": 0.03255184447126729,
    "val_recon": 0.029696579224296978,
    "dag_constraint": 0.0,
    "time_s": 0.24599695205688477
  },
  {
    "epoch": 121,
    "train_total": 0.03231522423448041,
    "train_recon": 0.0291825826279819,
    "train_transition": 0.003132641490083188,
    "train_dag": 0.0,
    "train_contrastive": 0.0,
    "val_total": 0.031969885740961344,
    "val_recon": 0.02911028771528176,
    "dag_constraint": 0.0,
    "time_s": 0.2470393180847168
  },
  {
    "epoch": 122,
    "train_total": 0.032019480073358864,
    "train_recon": 0.028868070046883076,
    "train_transition": 0.0031514099246123806,
    "train_dag": 0.0,
    "train_contrastive": 0.0,
    "val_total": 0.03253013880125114,
    "val_recon": 0.029743841184037074,
    "dag_constraint": 0.0,
    "time_s": 0.24707889556884766
  },
  {
    "epoch": 123,
    "train_total": 0.03147807403001934,
    "train_recon": 0.028359353193081915,
    "train_transition": 0.003118720807833597,
    "train_dag": 0.0,
    "train_contrastive": 0.0,
    "val_total": 0.03139217437377998,
    "val_recon": 0.028673768575702394,
    "dag_constraint": 0.0,
    "time_s": 0.2515866756439209
  },
  {
    "epoch": 124,
    "train_total": 0.031712213007267565,
    "train_recon": 0.02867885207524523,
    "train_transition": 0.003033360990229994,
    "train_dag": 0.0,
    "train_contrastive": 0.0,
    "val_total": 0.032748584768601825,
    "val_recon": 0.02993689477443695,
    "dag_constraint": 0.0,
    "time_s": 0.2560079097747803
  },
  {
    "epoch": 125,
    "train_total": 0.03134488605428487,
    "train_recon": 0.02833562792511657,
    "train_transition": 0.0030092580564087257,
    "train_dag": 0.0,
    "train_contrastive": 0.0,
    "val_total": 0.03252909279295376,
    "val_recon": 0.029770132952502797,
    "dag_constraint": 0.0,
    "time_s": 0.24959397315979004
  },
  {
    "epoch": 126,
    "train_total": 0.03172824362991378,
    "train_recon": 0.02867740165675059,
    "train_transition": 0.0030508420895785093,
    "train_dag": 0.0,
    "train_contrastive": 0.0,
    "val_total": 0.031837665875043185,
    "val_recon": 0.029140650161675045,
    "dag_constraint": 0.0,
    "time_s": 0.25026369094848633
  },
  {
    "epoch": 127,
    "train_total": 0.03147540317149833,
    "train_recon": 0.028483231842983514,
    "train_transition": 0.002992171619553119,
    "train_dag": 0.0,
    "train_contrastive": 0.0,
    "val_total": 0.03136943041213921,
    "val_recon": 0.028697246153439795,
    "dag_constraint": 0.0,
    "time_s": 0.2620077133178711
  },
  {
    "epoch": 128,
    "train_total": 0.031609353492967784,
    "train_recon": 0.028622193378396332,
    "train_transition": 0.002987160172779113,
    "train_dag": 0.0,
    "train_contrastive": 0.0,
    "val_total": 0.03094122824924333,
    "val_recon": 0.028230285005910054,
    "dag_constraint": 0.0,
    "time_s": 0.2572484016418457
  },
  {
    "epoch": 129,
    "train_total": 0.0323945835698396,
    "train_recon": 0.029372872377280146,
    "train_transition": 0.0030217112216632813,
    "train_dag": 0.0,
    "train_contrastive": 0.0,
    "val_total": 0.03206287696957588,
    "val_recon": 0.02937500604561397,
    "dag_constraint": 0.0,
    "time_s": 0.2496492862701416
  },
  {
    "epoch": 130,
    "train_total": 0.03226746781729162,
    "train_recon": 0.029274549626279622,
    "train_transition": 0.0029929180745966733,
    "train_dag": 0.0,
    "train_contrastive": 0.0,
    "val_total": 0.03187528784785952,
    "val_recon": 0.029165957123041153,
    "dag_constraint": 0.0,
    "time_s": 0.25673413276672363
  },
  {
    "epoch": 131,
    "train_total": 0.03149603819474578,
    "train_recon": 0.028537063219118863,
    "train_transition": 0.0029589750192826614,
    "train_dag": 0.0,
    "train_contrastive": 0.0,
    "val_total": 0.03144839512450354,
    "val_recon": 0.028812389288629805,
    "dag_constraint": 0.0,
    "time_s": 0.2525153160095215
  },
  {
    "epoch": 132,
    "train_total": 0.03143776237266138,
    "train_recon": 0.02847348595969379,
    "train_transition": 0.002964276383863762,
    "train_dag": 0.0,
    "train_contrastive": 0.0,
    "val_total": 0.03147264676434653,
    "val_recon": 0.028905667098505155,
    "dag_constraint": 0.0,
    "time_s": 0.2529788017272949
  },
  {
    "epoch": 133,
    "train_total": 0.03145800268976018,
    "train_recon": 0.028523444081656635,
    "train_transition": 0.002934558506240137,
    "train_dag": 0.0,
    "train_contrastive": 0.0,
    "val_total": 0.03175240941345692,
    "val_recon": 0.029178748971649578,
    "dag_constraint": 0.0,
    "time_s": 0.25133490562438965
  },
  {
    "epoch": 134,
    "train_total": 0.031812315341085196,
    "train_recon": 0.028892115398775786,
    "train_transition": 0.002920200160588138,
    "train_dag": 0.0,
    "train_contrastive": 0.0,
    "val_total": 0.031421485490032604,
    "val_recon": 0.028873237914272716,
    "dag_constraint": 0.0,
    "time_s": 0.25102663040161133
  },
  {
    "epoch": 135,
    "train_total": 0.03094199305633083,
    "train_recon": 0.02805975783849135,
    "train_transition": 0.002882235377910547,
    "train_dag": 0.0,
    "train_contrastive": 0.0,
    "val_total": 0.03056019571210657,
    "val_recon": 0.028085536988718168,
    "dag_constraint": 0.0,
    "time_s": 0.2530655860900879
  },
  {
    "epoch": 136,
    "train_total": 0.03129404073115438,
    "train_recon": 0.028402726456988603,
    "train_transition": 0.0028913143469253555,
    "train_dag": 0.0,
    "train_contrastive": 0.0,
    "val_total": 0.031646394836051125,
    "val_recon": 0.029178245791367123,
    "dag_constraint": 0.0,
    "time_s": 0.2605109214782715
  },
  {
    "epoch": 137,
    "train_total": 0.03157182125141844,
    "train_recon": 0.028696305642370135,
    "train_transition": 0.0028755155944963917,
    "train_dag": 0.0,
    "train_contrastive": 0.0,
    "val_total": 0.03110183429505144,
    "val_recon": 0.028477325503315245,
    "dag_constraint": 0.0,
    "time_s": 0.25458216667175293
  },
  {
    "epoch": 138,
    "train_total": 0.03106919425772503,
    "train_recon": 0.02820784703362733,
    "train_transition": 0.0028613476461032405,
    "train_dag": 0.0,
    "train_contrastive": 0.0,
    "val_total": 0.030432028962033137,
    "val_recon": 0.02794270989085947,
    "dag_constraint": 0.0,
    "time_s": 0.2517673969268799
  },
  {
    "epoch": 139,
    "train_total": 0.031119987135753036,
    "train_recon": 0.028281460283324122,
    "train_transition": 0.0028385268669808283,
    "train_dag": 0.0,
    "train_contrastive": 0.0,
    "val_total": 0.03143540902861527,
    "val_recon": 0.02897474861570767,
    "dag_constraint": 0.0,
    "time_s": 0.2516601085662842
  },
  {
    "epoch": 140,
    "train_total": 0.031137403508182615,
    "train_recon": 0.028348575462587178,
    "train_transition": 0.0027888281329069287,
    "train_dag": 0.0,
    "train_contrastive": 0.0,
    "val_total": 0.030937246180006435,
    "val_recon": 0.028510133336697305,
    "dag_constraint": 0.0,
    "time_s": 0.2520418167114258
  },
  {
    "epoch": 141,
    "train_total": 0.031108895025681704,
    "train_recon": 0.028324129758402705,
    "train_transition": 0.002784765194519423,
    "train_dag": 0.0,
    "train_contrastive": 0.0,
    "val_total": 0.03104415349662304,
    "val_recon": 0.028501692893249646,
    "dag_constraint": 0.0,
    "time_s": 0.2507607936859131
  },
  {
    "epoch": 142,
    "train_total": 0.031071171164512634,
    "train_recon": 0.02828989428235218,
    "train_transition": 0.0027812764747068286,
    "train_dag": 0.0,
    "train_contrastive": 0.0,
    "val_total": 0.031576567728604586,
    "val_recon": 0.029067385409559523,
    "dag_constraint": 0.0,
    "time_s": 0.24631881713867188
  },
  {
    "epoch": 143,
    "train_total": 0.030966465594246984,
    "train_recon": 0.02819573594024405,
    "train_transition": 0.0027707297849701717,
    "train_dag": 0.0,
    "train_contrastive": 0.0,
    "val_total": 0.03128299729100296,
    "val_recon": 0.028782069416982786,
    "dag_constraint": 0.0,
    "time_s": 0.2472386360168457
  },
  {
    "epoch": 144,
    "train_total": 0.03187606547726318,
    "train_recon": 0.029081302345730364,
    "train_transition": 0.002794762753183022,
    "train_dag": 0.0,
    "train_contrastive": 0.0,
    "val_total": 0.030793778598308563,
    "val_recon": 0.028362752071448734,
    "dag_constraint": 0.0,
    "time_s": 0.2505371570587158
  },
  {
    "epoch": 145,
    "train_total": 0.031154779077041894,
    "train_recon": 0.028410193568561226,
    "train_transition": 0.0027445857267593965,
    "train_dag": 0.0,
    "train_contrastive": 0.0,
    "val_total": 0.03161940909922123,
    "val_recon": 0.029203025890248164,
    "dag_constraint": 0.0,
    "time_s": 0.248077392578125
  },
  {
    "epoch": 146,
    "train_total": 0.031241867342032492,
    "train_recon": 0.028537622652947903,
    "train_transition": 0.0027042450237786397,
    "train_dag": 0.0,
    "train_contrastive": 0.0,
    "val_total": 0.03163556754589081,
    "val_recon": 0.029162189524088587,
    "dag_constraint": 0.0,
    "time_s": 0.24758315086364746
  },
  {
    "epoch": 147,
    "train_total": 0.03080779407173395,
    "train_recon": 0.028056304494384676,
    "train_transition": 0.0027514895336935297,
    "train_dag": 0.0,
    "train_contrastive": 0.0,
    "val_total": 0.031113434050764357,
    "val_recon": 0.028670656893934523,
    "dag_constraint": 0.0,
    "time_s": 0.2452995777130127
  },
  {
    "epoch": 148,
    "train_total": 0.031208575004711747,
    "train_recon": 0.028468255477491766,
    "train_transition": 0.0027403198037063703,
    "train_dag": 0.0,
    "train_contrastive": 0.0,
    "val_total": 0.030946157074400356,
    "val_recon": 0.028504329600504467,
    "dag_constraint": 0.0,
    "time_s": 0.2469182014465332
  },
  {
    "epoch": 149,
    "train_total": 0.03116387879708782,
    "train_recon": 0.028483630798291415,
    "train_transition": 0.0026802481152117252,
    "train_dag": 0.0,
    "train_contrastive": 0.0,
    "val_total": 0.031326357807431905,
    "val_recon": 0.028936663376433507,
    "dag_constraint": 0.0,
    "time_s": 0.24833941459655762
  },
  {
    "epoch": 150,
    "train_total": 0.03133788250852376,
    "train_recon": 0.02859385876217857,
    "train_transition": 0.0027440237026894465,
    "train_dag": 0.0,
    "train_contrastive": 0.0,
    "val_total": 0.030664369197828428,
    "val_recon": 0.02833132738513606,
    "dag_constraint": 0.0,
    "time_s": 0.24533891677856445
  },
  {
    "epoch": 151,
    "train_total": 0.03051666438113898,
    "train_recon": 0.027828332618810236,
    "train_transition": 0.002688331704121083,
    "train_dag": 0.0,
    "train_contrastive": 0.0,
    "val_total": 0.030513015442660878,
    "val_recon": 0.028161275067499707,
    "dag_constraint": 0.0,
    "time_s": 0.24296259880065918
  },
  {
    "epoch": 152,
    "train_total": 0.03144070622511208,
    "train_recon": 0.02880135941086337,
    "train_transition": 0.002639346945215948,
    "train_dag": 0.0,
    "train_contrastive": 0.0,
    "val_total": 0.03168089155639921,
    "val_recon": 0.029241546456302916,
    "dag_constraint": 0.0,
    "time_s": 0.24031591415405273
  },
  {
    "epoch": 153,
    "train_total": 0.031331833684816957,
    "train_recon": 0.028640897944569588,
    "train_transition": 0.0026909357256954536,
    "train_dag": 0.0,
    "train_contrastive": 0.0,
    "val_total": 0.03159122621374471,
    "val_recon": 0.029206323570438793,
    "dag_constraint": 0.0,
    "time_s": 0.24507451057434082
  },
  {
    "epoch": 154,
    "train_total": 0.030605462554376572,
    "train_recon": 0.027985574444755912,
    "train_transition": 0.002619888211484067,
    "train_dag": 0.0,
    "train_contrastive": 0.0,
    "val_total": 0.0311069767922163,
    "val_recon": 0.028734998777508736,
    "dag_constraint": 0.0,
    "time_s": 0.24965643882751465
  },
  {
    "epoch": 155,
    "train_total": 0.03092821128666401,
    "train_recon": 0.028254825447220355,
    "train_transition": 0.0026733858685474843,
    "train_dag": 0.0,
    "train_contrastive": 0.0,
    "val_total": 0.03029704572899001,
    "val_recon": 0.027969061263969967,
    "dag_constraint": 0.0,
    "time_s": 0.24930453300476074
  },
  {
    "epoch": 156,
    "train_total": 0.03077110048616305,
    "train_recon": 0.028196524071972817,
    "train_transition": 0.0025745762104634196,
    "train_dag": 0.0,
    "train_contrastive": 0.0,
    "val_total": 0.031424645866666524,
    "val_recon": 0.029060469940304756,
    "dag_constraint": 0.0,
    "time_s": 0.2547774314880371
  },
  {
    "epoch": 157,
    "train_total": 0.031137881858740002,
    "train_recon": 0.028512232936918736,
    "train_transition": 0.002625648907269351,
    "train_dag": 0.0,
    "train_contrastive": 0.0,
    "val_total": 0.030848035854952677,
    "val_recon": 0.028505062152232443,
    "dag_constraint": 0.0,
    "time_s": 0.2539823055267334
  },
  {
    "epoch": 158,
    "train_total": 0.031164482177700847,
    "train_recon": 0.02858677599579096,
    "train_transition": 0.002577706443844363,
    "train_dag": 0.0,
    "train_contrastive": 0.0,
    "val_total": 0.03045591845044068,
    "val_recon": 0.028113606785024916,
    "dag_constraint": 0.0,
    "time_s": 0.24944663047790527
  },
  {
    "epoch": 159,
    "train_total": 0.030709277896676213,
    "train_recon": 0.02807902795029804,
    "train_transition": 0.0026302500627934933,
    "train_dag": 0.0,
    "train_contrastive": 0.0,
    "val_total": 0.030201849128518785,
    "val_recon": 0.027965260137404715,
    "dag_constraint": 0.0,
    "time_s": 0.2512218952178955
  },
  {
    "epoch": 160,
    "train_total": 0.030594209034461528,
    "train_recon": 0.028020425292197615,
    "train_transition": 0.0025737838295754045,
    "train_dag": 0.0,
    "train_contrastive": 0.0,
    "val_total": 0.030729666352272034,
    "val_recon": 0.028479253873229027,
    "dag_constraint": 0.0,
    "time_s": 0.2521333694458008
  },
  {
    "epoch": 161,
    "train_total": 0.03069747774861753,
    "train_recon": 0.02818559540901333,
    "train_transition": 0.0025118824414676055,
    "train_dag": 0.0,
    "train_contrastive": 0.0,
    "val_total": 0.030301237212760106,
    "val_recon": 0.02804834848003728,
    "dag_constraint": 0.0,
    "time_s": 0.25116801261901855
  },
  {
    "epoch": 162,
    "train_total": 0.030401189695112407,
    "train_recon": 0.027856233820784837,
    "train_transition": 0.0025449560343986377,
    "train_dag": 0.0,
    "train_contrastive": 0.0,
    "val_total": 0.03032877668738365,
    "val_recon": 0.028062385639974048,
    "dag_constraint": 0.0,
    "time_s": 0.24868392944335938
  },
  {
    "epoch": 163,
    "train_total": 0.030956016504205763,
    "train_recon": 0.028412041487172246,
    "train_transition": 0.0025439750752411783,
    "train_dag": 0.0,
    "train_contrastive": 0.0,
    "val_total": 0.029802949833018438,
    "val_recon": 0.027543950027653148,
    "dag_constraint": 0.0,
    "time_s": 0.25041842460632324
  },
  {
    "epoch": 164,
    "train_total": 0.031015888089314103,
    "train_recon": 0.028448929078876972,
    "train_transition": 0.002566959068644792,
    "train_dag": 0.0,
    "train_contrastive": 0.0,
    "val_total": 0.03088747603552682,
    "val_recon": 0.028629938938788006,
    "dag_constraint": 0.0,
    "time_s": 0.25098156929016113
  },
  {
    "epoch": 165,
    "train_total": 0.03045088640647009,
    "train_recon": 0.027969316113740206,
    "train_transition": 0.002481570394593291,
    "train_dag": 0.0,
    "train_contrastive": 0.0,
    "val_total": 0.03021732158958912,
    "val_recon": 0.027960883719580516,
    "dag_constraint": 0.0,
    "time_s": 0.25664496421813965
  },
  {
    "epoch": 166,
    "train_total": 0.03063830581959337,
    "train_recon": 0.028114385902881622,
    "train_transition": 0.002523920120438561,
    "train_dag": 0.0,
    "train_contrastive": 0.0,
    "val_total": 0.0326720518725259,
    "val_recon": 0.030349889770150185,
    "dag_constraint": 0.0,
    "time_s": 0.25491809844970703
  },
  {
    "epoch": 167,
    "train_total": 0.03113134962040931,
    "train_recon": 0.028640075004659593,
    "train_transition": 0.002491274703061208,
    "train_dag": 0.0,
    "train_contrastive": 0.0,
    "val_total": 0.03052615693637303,
    "val_recon": 0.028235781671745435,
    "dag_constraint": 0.0,
    "time_s": 0.26517319679260254
  },
  {
    "epoch": 168,
    "train_total": 0.0306280434015207,
    "train_recon": 0.028139629983343184,
    "train_transition": 0.002488413389073685,
    "train_dag": 0.0,
    "train_contrastive": 0.0,
    "val_total": 0.03095087275973388,
    "val_recon": 0.028692398220300674,
    "dag_constraint": 0.0,
    "time_s": 0.25963568687438965
  },
  {
    "epoch": 169,
    "train_total": 0.030407860118430108,
    "train_recon": 0.027933547273278236,
    "train_transition": 0.0024743128597037867,
    "train_dag": 0.0,
    "train_contrastive": 0.0,
    "val_total": 0.030055095574685504,
    "val_recon": 0.027814260018723353,
    "dag_constraint": 0.0,
    "time_s": 0.2527029514312744
  },
  {
    "epoch": 170,
    "train_total": 0.03040179004892707,
    "train_recon": 0.027932742435950786,
    "train_transition": 0.0024690477875992656,
    "train_dag": 0.0,
    "train_contrastive": 0.0,
    "val_total": 0.0309417402105672,
    "val_recon": 0.028705093743545667,
    "dag_constraint": 0.0,
    "time_s": 0.2498631477355957
  },
  {
    "epoch": 171,
    "train_total": 0.030451110273133963,
    "train_recon": 0.02797639468917623,
    "train_transition": 0.0024747158749960363,
    "train_dag": 0.0,
    "train_contrastive": 0.0,
    "val_total": 0.030082732439041138,
    "val_recon": 0.027888703293034008,
    "dag_constraint": 0.0,
    "time_s": 0.2572765350341797
  },
  {
    "epoch": 172,
    "train_total": 0.030536352249328047,
    "train_recon": 0.028094670735299587,
    "train_transition": 0.002441681470372714,
    "train_dag": 0.0,
    "train_contrastive": 0.0,
    "val_total": 0.030194878578186035,
    "val_recon": 0.02798838461084025,
    "dag_constraint": 0.0,
    "time_s": 0.2555410861968994
  },
  {
    "epoch": 173,
    "train_total": 0.030593177012633532,
    "train_recon": 0.02817521372344345,
    "train_transition": 0.0024179631291190162,
    "train_dag": 0.0,
    "train_contrastive": 0.0,
    "val_total": 0.03008519804903439,
    "val_recon": 0.027895800503236905,
    "dag_constraint": 0.0,
    "time_s": 0.2563035488128662
  },
  {
    "epoch": 174,
    "train_total": 0.03036788327153772,
    "train_recon": 0.027948193601332605,
    "train_transition": 0.002419689655653201,
    "train_dag": 0.0,
    "train_contrastive": 0.0,
    "val_total": 0.030263497893299376,
    "val_recon": 0.028085305488535335,
    "dag_constraint": 0.0,
    "time_s": 0.2524840831756592
  },
  {
    "epoch": 175,
    "train_total": 0.030403737968299538,
    "train_recon": 0.027966621913947165,
    "train_transition": 0.002437115923385136,
    "train_dag": 0.0,
    "train_contrastive": 0.0,
    "val_total": 0.03128299542835781,
    "val_recon": 0.029066506241049086,
    "dag_constraint": 0.0,
    "time_s": 0.2519717216491699
  },
  {
    "epoch": 176,
    "train_total": 0.030786988500040025,
    "train_recon": 0.02837847516639158,
    "train_transition": 0.0024085132754407823,
    "train_dag": 0.0,
    "train_contrastive": 0.0,
    "val_total": 0.030102419799992015,
    "val_recon": 0.027922178485563824,
    "dag_constraint": 0.0,
    "time_s": 0.2538421154022217
  },
  {
    "epoch": 177,
    "train_total": 0.03004855487961322,
    "train_recon": 0.027626762224826962,
    "train_transition": 0.002421792654786259,
    "train_dag": 0.0,
    "train_contrastive": 0.0,
    "val_total": 0.02985187087740217,
    "val_recon": 0.027713875153235028,
    "dag_constraint": 0.0,
    "time_s": 0.25650978088378906
  },
  {
    "epoch": 178,
    "train_total": 0.03015257033985108,
    "train_recon": 0.02775937400292605,
    "train_transition": 0.0023931964387884364,
    "train_dag": 0.0,
    "train_contrastive": 0.0,
    "val_total": 0.030457435974052975,
    "val_recon": 0.02835221721657685,
    "dag_constraint": 0.0,
    "time_s": 0.25203871726989746
  },
  {
    "epoch": 179,
    "train_total": 0.030332700291182846,
    "train_recon": 0.02797114849090576,
    "train_transition": 0.002361551465583034,
    "train_dag": 0.0,
    "train_contrastive": 0.0,
    "val_total": 0.030103703428592,
    "val_recon": 0.02795863151550293,
    "dag_constraint": 0.0,
    "time_s": 0.25063180923461914
  },
  {
    "epoch": 180,
    "train_total": 0.02985272230580449,
    "train_recon": 0.027497439412400126,
    "train_transition": 0.0023552827478852123,
    "train_dag": 0.0,
    "train_contrastive": 0.0,
    "val_total": 0.029419644868799617,
    "val_recon": 0.027294946302260672,
    "dag_constraint": 0.0,
    "time_s": 0.2505981922149658
  },
  {
    "epoch": 181,
    "train_total": 0.030095271533355117,
    "train_recon": 0.027764893835410476,
    "train_transition": 0.0023303775960812345,
    "train_dag": 0.0,
    "train_contrastive": 0.0,
    "val_total": 0.030100776946970394,
    "val_recon": 0.028022473145808493,
    "dag_constraint": 0.0,
    "time_s": 0.25493597984313965
  },
  {
    "epoch": 182,
    "train_total": 0.030120639828965068,
    "train_recon": 0.02779363456647843,
    "train_transition": 0.0023270053206942976,
    "train_dag": 0.0,
    "train_contrastive": 0.0,
    "val_total": 0.030317970418504307,
    "val_recon": 0.02816603279539517,
    "dag_constraint": 0.0,
    "time_s": 0.2497272491455078
  },
  {
    "epoch": 183,
    "train_total": 0.030013245763257146,
    "train_recon": 0.02771845366805792,
    "train_transition": 0.0022947922261664644,
    "train_dag": 0.0,
    "train_contrastive": 0.0,
    "val_total": 0.030387993901968002,
    "val_recon": 0.028153777920774052,
    "dag_constraint": 0.0,
    "time_s": 0.2546074390411377
  },
  {
    "epoch": 184,
    "train_total": 0.03003401041496545,
    "train_recon": 0.027698552643414587,
    "train_transition": 0.0023354575532721356,
    "train_dag": 0.0,
    "train_contrastive": 0.0,
    "val_total": 0.02963449539882796,
    "val_recon": 0.02755440159567765,
    "dag_constraint": 0.0,
    "time_s": 0.2537205219268799
  },
  {
    "epoch": 185,
    "train_total": 0.03008322708774358,
    "train_recon": 0.027744808699935675,
    "train_transition": 0.002338418285944499,
    "train_dag": 0.0,
    "train_contrastive": 0.0,
    "val_total": 0.030877338722348213,
    "val_recon": 0.028856741530554637,
    "dag_constraint": 0.0,
    "time_s": 0.25511932373046875
  },
  {
    "epoch": 186,
    "train_total": 0.030225220194552094,
    "train_recon": 0.027899258537217975,
    "train_transition": 0.002325961773749441,
    "train_dag": 0.0,
    "train_contrastive": 0.0,
    "val_total": 0.029998368450573513,
    "val_recon": 0.02795764777277197,
    "dag_constraint": 0.0,
    "time_s": 0.25191640853881836
  },
  {
    "epoch": 187,
    "train_total": 0.030534207704477012,
    "train_recon": 0.028216560545843095,
    "train_transition": 0.002317646925803274,
    "train_dag": 0.0,
    "train_contrastive": 0.0,
    "val_total": 0.031317912840417454,
    "val_recon": 0.029248712052192007,
    "dag_constraint": 0.0,
    "time_s": 0.2530081272125244
  },
  {
    "epoch": 188,
    "train_total": 0.030926655628718436,
    "train_recon": 0.028607120388187468,
    "train_transition": 0.0023195353423943743,
    "train_dag": 0.0,
    "train_contrastive": 0.0,
    "val_total": 0.030219559956874167,
    "val_recon": 0.02817328753215926,
    "dag_constraint": 0.0,
    "time_s": 0.2517735958099365
  },
  {
    "epoch": 189,
    "train_total": 0.030398155911825597,
    "train_recon": 0.02805227437056601,
    "train_transition": 0.0023458817013306543,
    "train_dag": 0.0,
    "train_contrastive": 0.0,
    "val_total": 0.03151974880269596,
    "val_recon": 0.029308306319372996,
    "dag_constraint": 0.0,
    "time_s": 0.2510983943939209
  },
  {
    "epoch": 190,
    "train_total": 0.03005290520377457,
    "train_recon": 0.02776153665035963,
    "train_transition": 0.0022913685825187713,
    "train_dag": 0.0,
    "train_contrastive": 0.0,
    "val_total": 0.029494905578238622,
    "val_recon": 0.027430255498204912,
    "dag_constraint": 0.0,
    "time_s": 0.24807024002075195
  },
  {
    "epoch": 191,
    "train_total": 0.030087596736848354,
    "train_recon": 0.02779461699537933,
    "train_transition": 0.0022929797269171104,
    "train_dag": 0.0,
    "train_contrastive": 0.0,
    "val_total": 0.03004785786781992,
    "val_recon": 0.02797189008976732,
    "dag_constraint": 0.0,
    "time_s": 0.2474195957183838
  },
  {
    "epoch": 192,
    "train_total": 0.030186565360054374,
    "train_recon": 0.027886855707038194,
    "train_transition": 0.002299709420185536,
    "train_dag": 0.0,
    "train_contrastive": 0.0,
    "val_total": 0.030706197821668217,
    "val_recon": 0.028661793363945826,
    "dag_constraint": 0.0,
    "time_s": 0.2508280277252197
  },
  {
    "epoch": 193,
    "train_total": 0.02990845841122791,
    "train_recon": 0.027637301885988563,
    "train_transition": 0.0022711563360644504,
    "train_dag": 0.0,
    "train_contrastive": 0.0,
    "val_total": 0.029975558231983866,
    "val_recon": 0.02793338256222861,
    "dag_constraint": 0.0,
    "time_s": 0.2539210319519043
  },
  {
    "epoch": 194,
    "train_total": 0.02982629562029615,
    "train_recon": 0.027595469902735204,
    "train_transition": 0.0022308256156975403,
    "train_dag": 0.0,
    "train_contrastive": 0.0,
    "val_total": 0.029788901497210776,
    "val_recon": 0.02776855230331421,
    "dag_constraint": 0.0,
    "time_s": 0.25333642959594727
  },
  {
    "epoch": 195,
    "train_total": 0.029964899003971368,
    "train_recon": 0.02771364478394389,
    "train_transition": 0.002251254307338968,
    "train_dag": 0.0,
    "train_contrastive": 0.0,
    "val_total": 0.0303747970610857,
    "val_recon": 0.028359404632023404,
    "dag_constraint": 0.0,
    "time_s": 0.2558560371398926
  },
  {
    "epoch": 196,
    "train_total": 0.03067274542991072,
    "train_recon": 0.02840640692738816,
    "train_transition": 0.002266338444314897,
    "train_dag": 0.0,
    "train_contrastive": 0.0,
    "val_total": 0.02952491438814572,
    "val_recon": 0.0275048025484596,
    "dag_constraint": 0.0,
    "time_s": 0.250978946685791
  },
  {
    "epoch": 197,
    "train_total": 0.03000399307347834,
    "train_recon": 0.027766592742409557,
    "train_transition": 0.00223740006913431,
    "train_dag": 0.0,
    "train_contrastive": 0.0,
    "val_total": 0.02978259644338063,
    "val_recon": 0.02774276797260557,
    "dag_constraint": 0.0,
    "time_s": 0.25330042839050293
  },
  {
    "epoch": 198,
    "train_total": 0.02951615070924163,
    "train_recon": 0.02727012720424682,
    "train_transition": 0.002246023650513962,
    "train_dag": 0.0,
    "train_contrastive": 0.0,
    "val_total": 0.030418628826737404,
    "val_recon": 0.02836399312530245,
    "dag_constraint": 0.0,
    "time_s": 0.25098705291748047
  },
  {
    "epoch": 199,
    "train_total": 0.02978255460038781,
    "train_recon": 0.027578029897995293,
    "train_transition": 0.0022045246296329424,
    "train_dag": 0.0,
    "train_contrastive": 0.0,
    "val_total": 0.029435566759535244,
    "val_recon": 0.027478821575641632,
    "dag_constraint": 0.0,
    "time_s": 0.24700641632080078
  },
  {
    "epoch": 200,
    "train_total": 0.029645316360983998,
    "train_recon": 0.027446602121926844,
    "train_transition": 0.0021987143845763057,
    "train_dag": 0.0,
    "train_contrastive": 0.0,
    "val_total": 0.030518620940191404,
    "val_recon": 0.028579970289553915,
    "dag_constraint": 0.0,
    "time_s": 0.24498605728149414
  }
]