[
  {
    "epoch": 1,
    "train_total": 0.1289757969789207,
    "train_recon": 0.08351700217463076,
    "train_transition": 0.04545879480428994,
    "train_dag": 0.0,
    "train_contrastive": 0.0,
    "val_total": 0.08822362550667354,
    "val_recon": 0.07581148988434247,
    "dag_constraint": 0.0,
    "time_s": 0.2541921138763428
  },
  {
    "epoch": 2,
    "train_total": 0.0877569536678493,
    "train_recon": 0.07806981983594596,
    "train_transition": 0.009687133395345882,
    "train_dag": 0.0,
    "train_contrastive": 0.0,
    "val_total": 0.080016128718853,
    "val_recon": 0.07345614050115858,
    "dag_constraint": 0.0,
    "time_s": 0.253371000289917
  },
  {
    "epoch": 3,
    "train_total": 0.08217849326319993,
    "train_recon": 0.07577809737995267,
    "train_transition": 0.006400396901881322,
    "train_dag": 0.0,
    "train_contrastive": 0.0,
    "val_total": 0.07621995519314494,
    "val_recon": 0.071151145866939,
    "dag_constraint": 0.0,
    "time_s": 0.2607598304748535
  },
  {
    "epoch": 4,
    "train_total": 0.07793237874284387,
    "train_recon": 0.07256269291974604,
    "train_transition": 0.005369685561163351,
    "train_dag": 0.0,
    "train_contrastive": 0.0,
    "val_total": 0.07255788945725986,
    "val_recon": 0.0679570415190288,
    "dag_constraint": 0.0,
    "time_s": 0.2518177032470703
  },
  {
    "epoch": 5,
    "train_total": 0.07358243502676487,
    "train_recon": 0.06835591560229659,
    "train_transition": 0.005226519235293381,
    "train_dag": 0.0,
    "train_contrastive": 0.0,
    "val_total": 0.06880381650158338,
    "val_recon": 0.06401132472923823,
    "dag_constraint": 0.0,
    "time_s": 0.2543008327484131
  },
  {
    "epoch": 6,
    "train_total": 0.06947656720876694,
    "train_recon": 0.06371106475125998,
    "train_transition": 0.005765501991845667,
    "train_dag": 0.0,
    "train_contrastive": 0.0,
    "val_total": 0.06478937555636678,
    "val_recon": 0.059423960745334625,
    "dag_constraint": 0.0,
    "time_s": 0.2494184970855713
  },
  {
    "epoch": 7,
    "train_total": 0.06508605752605945,
    "train_recon": 0.05880884756334126,
    "train_transition": 0.0062772094970569015,
    "train_dag": 0.0,
    "train_contrastive": 0.0,
    "val_total": 0.06068211793899536,
    "val_recon": 0.054838172027042935,
    "dag_constraint": 0.0,
    "time_s": 0.24992632865905762
  },
  {
    "epoch": 8,
    "train_total": 0.06090971257071942,
    "train_recon": 0.053963037906214595,
    "train_transition": 0.006946674315258861,
    "train_dag": 0.0,
    "train_contrastive": 0.0,
    "val_total": 0.05690661338823182,
    "val_recon": 0.050495803888354986,
    "dag_constraint": 0.0,
    "time_s": 0.24972271919250488
  },
  {
    "epoch": 9,
    "train_total": 0.05649055913090706,
    "train_recon": 0.04930107784457505,
    "train_transition": 0.007189481417299248,
    "train_dag": 0.0,
    "train_contrastive": 0.0,
    "val_total": 0.05283341503569058,
    "val_recon": 0.04611093071954591,
    "dag_constraint": 0.0,
    "time_s": 0.25426173210144043
  },
  {
    "epoch": 10,
    "train_total": 0.05302380211651325,
    "train_recon": 0.04583746800199151,
    "train_transition": 0.007186334463767707,
    "train_dag": 0.0,
    "train_contrastive": 0.0,
    "val_total": 0.04892809529389654,
    "val_recon": 0.04265268413083894,
    "dag_constraint": 0.0,
    "time_s": 0.2540714740753174
  },
  {
    "epoch": 11,
    "train_total": 0.04962849116418511,
    "train_recon": 0.04255848017055541,
    "train_transition": 0.007070011197356507,
    "train_dag": 0.0,
    "train_contrastive": 0.0,
    "val_total": 0.046717311654772074,
    "val_recon": 0.040764166308300834,
    "dag_constraint": 0.0,
    "time_s": 0.2538483142852783
  },
  {
    "epoch": 12,
    "train_total": 0.047029002802446485,
    "train_recon": 0.04029536072630435,
    "train_transition": 0.006733641755999997,
    "train_dag": 0.0,
    "train_contrastive": 0.0,
    "val_total": 0.04372689181140491,
    "val_recon": 0.03782553119318826,
    "dag_constraint": 0.0,
    "time_s": 0.2516665458679199
  },
  {
    "epoch": 13,
    "train_total": 0.04473817197140306,
    "train_recon": 0.03839842288289219,
    "train_transition": 0.006339749015751295,
    "train_dag": 0.0,
    "train_contrastive": 0.0,
    "val_total": 0.04367696759956224,
    "val_recon": 0.03783871978521347,
    "dag_constraint": 0.0,
    "time_s": 0.2514925003051758
  },
  {
    "epoch": 14,
    "train_total": 0.04340518033131957,
    "train_recon": 0.0373488575569354,
    "train_transition": 0.006056322992662899,
    "train_dag": 0.0,
    "train_contrastive": 0.0,
    "val_total": 0.04076591187289783,
    "val_recon": 0.03549021854996681,
    "dag_constraint": 0.0,
    "time_s": 0.24861621856689453
  },
  {
    "epoch": 15,
    "train_total": 0.04156840580981225,
    "train_recon": 0.03571773017756641,
    "train_transition": 0.005850675705005415,
    "train_dag": 0.0,
    "train_contrastive": 0.0,
    "val_total": 0.040197015340839116,
    "val_recon": 0.03508577070065907,
    "dag_constraint": 0.0,
    "time_s": 0.2521531581878662
  },
  {
    "epoch": 16,
    "train_total": 0.040228103869594634,
    "train_recon": 0.03472216834779829,
    "train_transition": 0.005505935157998465,
    "train_dag": 0.0,
    "train_contrastive": 0.0,
    "val_total": 0.03905855704631124,
    "val_recon": 0.03425002018255847,
    "dag_constraint": 0.0,
    "time_s": 0.25711870193481445
  },
  {
    "epoch": 17,
    "train_total": 0.039128935313783586,
    "train_recon": 0.033829580002930015,
    "train_transition": 0.005299355339957401,
    "train_dag": 0.0,
    "train_contrastive": 0.0,
    "val_total": 0.03750740896378245,
    "val_recon": 0.03296909800597599,
    "dag_constraint": 0.0,
    "time_s": 0.2554810047149658
  },
  {
    "epoch": 18,
    "train_total": 0.03800579544622451,
    "train_recon": 0.03298154805088416,
    "train_transition": 0.005024247337132692,
    "train_dag": 0.0,
    "train_contrastive": 0.0,
    "val_total": 0.03785369013037,
    "val_recon": 0.03352551508162703,
    "dag_constraint": 0.0,
    "time_s": 0.24909496307373047
  },
  {
    "epoch": 19,
    "train_total": 0.03673064784379676,
    "train_recon": 0.03190379322040826,
    "train_transition": 0.004826854870771058,
    "train_dag": 0.0,
    "train_contrastive": 0.0,
    "val_total": 0.03666097564356668,
    "val_recon": 0.03244997507759503,
    "dag_constraint": 0.0,
    "time_s": 0.2531147003173828
  },
  {
    "epoch": 20,
    "train_total": 0.03621689393185079,
    "train_recon": 0.03157546976581216,
    "train_transition": 0.0046414241078309715,
    "train_dag": 0.0,
    "train_contrastive": 0.0,
    "val_total": 0.03637564341936793,
    "val_recon": 0.03213583518351827,
    "dag_constraint": 0.0,
    "time_s": 0.25183963775634766
  },
  {
    "epoch": 21,
    "train_total": 0.03604257252300158,
    "train_recon": 0.03137939516454935,
    "train_transition": 0.0046631774748675525,
    "train_dag": 0.0,
    "train_contrastive": 0.0,
    "val_total": 0.034997900149651935,
    "val_recon": 0.030876500798123225,
    "dag_constraint": 0.0,
    "time_s": 0.2588920593261719
  },
  {
    "epoch": 22,
    "train_total": 0.03503584093414247,
    "train_recon": 0.03042403917061165,
    "train_transition": 0.004611801647115499,
    "train_dag": 0.0,
    "train_contrastive": 0.0,
    "val_total": 0.035531499556132724,
    "val_recon": 0.03132024221122265,
    "dag_constraint": 0.0,
    "time_s": 0.2528500556945801
  },
  {
    "epoch": 23,
    "train_total": 0.033714509452693164,
    "train_recon": 0.029204950609710068,
    "train_transition": 0.004509558988502249,
    "train_dag": 0.0,
    "train_contrastive": 0.0,
    "val_total": 0.03317443946642535,
    "val_recon": 0.02918978168496064,
    "dag_constraint": 0.0,
    "time_s": 0.25179386138916016
  },
  {
    "epoch": 24,
    "train_total": 0.03256539523135871,
    "train_recon": 0.028167441487312317,
    "train_transition": 0.004397953656734899,
    "train_dag": 0.0,
    "train_contrastive": 0.0,
    "val_total": 0.032849013805389404,
    "val_recon": 0.028981577338916913,
    "dag_constraint": 0.0,
    "time_s": 0.25681352615356445
  },
  {
    "epoch": 25,
    "train_total": 0.03218503505922854,
    "train_recon": 0.02792668907204643,
    "train_transition": 0.004258346089045517,
    "train_dag": 0.0,
    "train_contrastive": 0.0,
    "val_total": 0.03203210713607924,
    "val_recon": 0.028212267639381543,
    "dag_constraint": 0.0,
    "time_s": 0.2598557472229004
  },
  {
    "epoch": 26,
    "train_total": 0.031803238845895976,
    "train_recon": 0.02755445725051686,
    "train_transition": 0.004248781566275284,
    "train_dag": 0.0,
    "train_contrastive": 0.0,
    "val_total": 0.03179868417126792,
    "val_recon": 0.028124199115804265,
    "dag_constraint": 0.0,
    "time_s": 0.25344038009643555
  },
  {
    "epoch": 27,
    "train_total": 0.030900923418812454,
    "train_recon": 0.02677286951802671,
    "train_transition": 0.004128053842578083,
    "train_dag": 0.0,
    "train_contrastive": 0.0,
    "val_total": 0.031010285019874573,
    "val_recon": 0.02739373967051506,
    "dag_constraint": 0.0,
    "time_s": 0.25067949295043945
  },
  {
    "epoch": 28,
    "train_total": 0.031027205986902118,
    "train_recon": 0.026999190216884017,
    "train_transition": 0.004028016002848744,
    "train_dag": 0.0,
    "train_contrastive": 0.0,
    "val_total": 0.0321932706449713,
    "val_recon": 0.02856753527053765,
    "dag_constraint": 0.0,
    "time_s": 0.25163888931274414
  },
  {
    "epoch": 29,
    "train_total": 0.031355518847703934,
    "train_recon": 0.027354133140761405,
    "train_transition": 0.0040013853868003935,
    "train_dag": 0.0,
    "train_contrastive": 0.0,
    "val_total": 0.03139896956937654,
    "val_recon": 0.027772359549999237,
    "dag_constraint": 0.0,
    "time_s": 0.2536289691925049
  },
  {
    "epoch": 30,
    "train_total": 0.02996769978199154,
    "train_recon": 0.026228939357679337,
    "train_transition": 0.003738760278793052,
    "train_dag": 0.0,
    "train_contrastive": 0.0,
    "val_total": 0.03048326979790415,
    "val_recon": 0.027119717693754604,
    "dag_constraint": 0.0,
    "time_s": 0.25260424613952637
  },
  {
    "epoch": 31,
    "train_total": 0.02975048270309344,
    "train_recon": 0.026106046454515308,
    "train_transition": 0.003644436248578131,
    "train_dag": 0.0,
    "train_contrastive": 0.0,
    "val_total": 0.02972514501639775,
    "val_recon": 0.026457908430269787,
    "dag_constraint": 0.0,
    "time_s": 0.2533431053161621
  },
  {
    "epoch": 32,
    "train_total": 0.029878097062464803,
    "train_recon": 0.02629323344444856,
    "train_transition": 0.0035848637198796496,
    "train_dag": 0.0,
    "train_contrastive": 0.0,
    "val_total": 0.030599813908338547,
    "val_recon": 0.027381499164870808,
    "dag_constraint": 0.0,
    "time_s": 0.2548255920410156
  },
  {
    "epoch": 33,
    "train_total": 0.029538814502302557,
    "train_recon": 0.02595565898809582,
    "train_transition": 0.003583155485102907,
    "train_dag": 0.0,
    "train_contrastive": 0.0,
    "val_total": 0.029363288677164485,
    "val_recon": 0.02636019459792546,
    "dag_constraint": 0.0,
    "time_s": 0.25259876251220703
  },
  {
    "epoch": 34,
    "train_total": 0.02917233225889504,
    "train_recon": 0.025791963271331042,
    "train_transition": 0.0033803690457716584,
    "train_dag": 0.0,
    "train_contrastive": 0.0,
    "val_total": 0.030164075483168875,
    "val_recon": 0.027113061930452074,
    "dag_constraint": 0.0,
    "time_s": 0.2684786319732666
  },
  {
    "epoch": 35,
    "train_total": 0.029621616355143487,
    "train_recon": 0.026336161012295634,
    "train_transition": 0.003285455211880617,
    "train_dag": 0.0,
    "train_contrastive": 0.0,
    "val_total": 0.029303334653377533,
    "val_recon": 0.02639191970229149,
    "dag_constraint": 0.0,
    "time_s": 0.26477742195129395
  },
  {
    "epoch": 36,
    "train_total": 0.02926037641009316,
    "train_recon": 0.025951125659048557,
    "train_transition": 0.0033092507655965164,
    "train_dag": 0.0,
    "train_contrastive": 0.0,
    "val_total": 0.02868095359631947,
    "val_recon": 0.025813821969287738,
    "dag_constraint": 0.0,
    "time_s": 0.2582557201385498
  },
  {
    "epoch": 37,
    "train_total": 0.028316146868746728,
    "train_recon": 0.025187440391164273,
    "train_transition": 0.003128706506686285,
    "train_dag": 0.0,
    "train_contrastive": 0.0,
    "val_total": 0.028384846236024584,
    "val_recon": 0.025547114866120473,
    "dag_constraint": 0.0,
    "time_s": 0.25783777236938477
  },
  {
    "epoch": 38,
    "train_total": 0.02888842287939042,
    "train_recon": 0.02577236999059096,
    "train_transition": 0.003116052714176476,
    "train_dag": 0.0,
    "train_contrastive": 0.0,
    "val_total": 0.028405016554253443,
    "val_recon": 0.025678673493010656,
    "dag_constraint": 0.0,
    "time_s": 0.24928545951843262
  },
  {
    "epoch": 39,
    "train_total": 0.028150587109848857,
    "train_recon": 0.02513954183086753,
    "train_transition": 0.0030110453662928194,
    "train_dag": 0.0,
    "train_contrastive": 0.0,
    "val_total": 0.029374398025018827,
    "val_recon": 0.026698339730501175,
    "dag_constraint": 0.0,
    "time_s": 0.25117039680480957
  },
  {
    "epoch": 40,
    "train_total": 0.028154268104117364,
    "train_recon": 0.02515851001953706,
    "train_transition": 0.0029957579827168956,
    "train_dag": 0.0,
    "train_contrastive": 0.0,
    "val_total": 0.03044226180229868,
    "val_recon": 0.027558979179177965,
    "dag_constraint": 0.0,
    "time_s": 0.2528650760650635
  },
  {
    "epoch": 41,
    "train_total": 0.028262995008844882,
    "train_recon": 0.025362338579725474,
    "train_transition": 0.002900656225392595,
    "train_dag": 0.0,
    "train_contrastive": 0.0,
    "val_total": 0.028726637363433838,
    "val_recon": 0.026189114366258894,
    "dag_constraint": 0.0,
    "time_s": 0.24932146072387695
  },
  {
    "epoch": 42,
    "train_total": 0.02859594440087676,
    "train_recon": 0.025678058504126966,
    "train_transition": 0.0029178858239902183,
    "train_dag": 0.0,
    "train_contrastive": 0.0,
    "val_total": 0.02799926032977445,
    "val_recon": 0.0255154443106481,
    "dag_constraint": 0.0,
    "time_s": 0.25630617141723633
  },
  {
    "epoch": 43,
    "train_total": 0.02789599756943062,
    "train_recon": 0.025134395575150847,
    "train_transition": 0.0027616021543508396,
    "train_dag": 0.0,
    "train_contrastive": 0.0,
    "val_total": 0.02776406066758292,
    "val_recon": 0.025273528216140612,
    "dag_constraint": 0.0,
    "time_s": 0.25642991065979004
  },
  {
    "epoch": 44,
    "train_total": 0.02757720259251073,
    "train_recon": 0.024844625033438206,
    "train_transition": 0.002732577806455083,
    "train_dag": 0.0,
    "train_contrastive": 0.0,
    "val_total": 0.027786954173019955,
    "val_recon": 0.025386424203004156,
    "dag_constraint": 0.0,
    "time_s": 0.2508823871612549
  },
  {
    "epoch": 45,
    "train_total": 0.027395031531341374,
    "train_recon": 0.02474406687542796,
    "train_transition": 0.002650964743224904,
    "train_dag": 0.0,
    "train_contrastive": 0.0,
    "val_total": 0.02856247579412801,
    "val_recon": 0.026141030181731497,
    "dag_constraint": 0.0,
    "time_s": 0.24860048294067383
  },
  {
    "epoch": 46,
    "train_total": 0.027284056646749377,
    "train_recon": 0.0246859691105783,
    "train_transition": 0.0025980874488595873,
    "train_dag": 0.0,
    "train_contrastive": 0.0,
    "val_total": 0.02866608090698719,
    "val_recon": 0.026268508019191877,
    "dag_constraint": 0.0,
    "time_s": 0.2507786750793457
  },
  {
    "epoch": 47,
    "train_total": 0.027410586888436228,
    "train_recon": 0.024851145164575428,
    "train_transition": 0.0025594416802050546,
    "train_dag": 0.0,
    "train_contrastive": 0.0,
    "val_total": 0.027689024806022644,
    "val_recon": 0.025454826653003693,
    "dag_constraint": 0.0,
    "time_s": 0.2483515739440918
  },
  {
    "epoch": 48,
    "train_total": 0.027298017230350524,
    "train_recon": 0.024745298025663942,
    "train_transition": 0.0025527193502057344,
    "train_dag": 0.0,
    "train_contrastive": 0.0,
    "val_total": 0.028597119663442885,
    "val_recon": 0.02636031753250531,
    "dag_constraint": 0.0,
    "time_s": 0.2518284320831299
  },
  {
    "epoch": 49,
    "train_total": 0.02729708288097754,
    "train_recon": 0.024844903498888016,
    "train_transition": 0.0024521793820895255,
    "train_dag": 0.0,
    "train_contrastive": 0.0,
    "val_total": 0.028585387659924372,
    "val_recon": 0.026178527623414993,
    "dag_constraint": 0.0,
    "time_s": 0.25185537338256836
  },
  {
    "epoch": 50,
    "train_total": 0.027097477577626705,
    "train_recon": 0.024636244983412325,
    "train_transition": 0.0024612326378701255,
    "train_dag": 0.0,
    "train_contrastive": 0.0,
    "val_total": 0.027325633381094252,
    "val_recon": 0.025164988956281116,
    "dag_constraint": 0.0,
    "time_s": 0.2584383487701416
  },
  {
    "epoch": 51,
    "train_total": 0.02737035951577127,
    "train_recon": 0.024953949730843306,
    "train_transition": 0.0024164097994798794,
    "train_dag": 0.0,
    "train_contrastive": 0.0,
    "val_total": 0.02766623587480613,
    "val_recon": 0.025527641975453923,
    "dag_constraint": 0.0,
    "time_s": 0.25353479385375977
  },
  {
    "epoch": 52,
    "train_total": 0.027468823827803135,
    "train_recon": 0.02500005078036338,
    "train_transition": 0.0024687730183359236,
    "train_dag": 0.0,
    "train_contrastive": 0.0,
    "val_total": 0.02691173500248364,
    "val_recon": 0.02478531189262867,
    "dag_constraint": 0.0,
    "time_s": 0.2552506923675537
  },
  {
    "epoch": 53,
    "train_total": 0.026874730887357146,
    "train_recon": 0.024531000293791294,
    "train_transition": 0.0023437305790139362,
    "train_dag": 0.0,
    "train_contrastive": 0.0,
    "val_total": 0.027191366468157088,
    "val_recon": 0.025057798783693994,
    "dag_constraint": 0.0,
    "time_s": 0.25336194038391113
  },
  {
    "epoch": 54,
    "train_total": 0.02688937122002244,
    "train_recon": 0.024554397154133767,
    "train_transition": 0.002334973920369521,
    "train_dag": 0.0,
    "train_contrastive": 0.0,
    "val_total": 0.02747087925672531,
    "val_recon": 0.02541430400950568,
    "dag_constraint": 0.0,
    "time_s": 0.2523012161254883
  },
  {
    "epoch": 55,
    "train_total": 0.02656386053422466,
    "train_recon": 0.024337797658517957,
    "train_transition": 0.002226062846602872,
    "train_dag": 0.0,
    "train_contrastive": 0.0,
    "val_total": 0.026863160144005502,
    "val_recon": 0.024853528876389776,
    "dag_constraint": 0.0,
    "time_s": 0.2523539066314697
  },
  {
    "epoch": 56,
    "train_total": 0.026301370933651924,
    "train_recon": 0.024065112229436636,
    "train_transition": 0.002236258500488475,
    "train_dag": 0.0,
    "train_contrastive": 0.0,
    "val_total": 0.02655633964708873,
    "val_recon": 0.024572405964136124,
    "dag_constraint": 0.0,
    "time_s": 0.2529623508453369
  },
  {
    "epoch": 57,
    "train_total": 0.02617968386039138,
    "train_recon": 0.024027095234487206,
    "train_transition": 0.002152588655008003,
    "train_dag": 0.0,
    "train_contrastive": 0.0,
    "val_total": 0.027247157746127675,
    "val_recon": 0.025233964568802288,
    "dag_constraint": 0.0,
    "time_s": 0.25244784355163574
  },
  {
    "epoch": 58,
    "train_total": 0.02645723824389279,
    "train_recon": 0.024275125411804765,
    "train_transition": 0.002182112817536108,
    "train_dag": 0.0,
    "train_contrastive": 0.0,
    "val_total": 0.02765612064727715,
    "val_recon": 0.025623213233692304,
    "dag_constraint": 0.0,
    "time_s": 0.25223326683044434
  },
  {
    "epoch": 59,
    "train_total": 0.02675946126691997,
    "train_recon": 0.024588960979599506,
    "train_transition": 0.0021705002727685496,
    "train_dag": 0.0,
    "train_contrastive": 0.0,
    "val_total": 0.026567804227982248,
    "val_recon": 0.024611086451581547,
    "dag_constraint": 0.0,
    "time_s": 0.2546260356903076
  },
  {
    "epoch": 60,
    "train_total": 0.02673436264740303,
    "train_recon": 0.02455902937799692,
    "train_transition": 0.0021753331529907882,
    "train_dag": 0.0,
    "train_contrastive": 0.0,
    "val_total": 0.026908767010484422,
    "val_recon": 0.02495225359286581,
    "dag_constraint": 0.0,
    "time_s": 0.25069403648376465
  },
  {
    "epoch": 61,
    "train_total": 0.02633418730692938,
    "train_recon": 0.02427147387061268,
    "train_transition": 0.0020627134654205292,
    "train_dag": 0.0,
    "train_contrastive": 0.0,
    "val_total": 0.026837361178227832,
    "val_recon": 0.024907162146908895,
    "dag_constraint": 0.0,
    "time_s": 0.25142717361450195
  },
  {
    "epoch": 62,
    "train_total": 0.026238390360958874,
    "train_recon": 0.02417876635445282,
    "train_transition": 0.002059623846434988,
    "train_dag": 0.0,
    "train_contrastive": 0.0,
    "val_total": 0.02697553645287241,
    "val_recon": 0.025112265454871312,
    "dag_constraint": 0.0,
    "time_s": 0.24745726585388184
  },
  {
    "epoch": 63,
    "train_total": 0.026040216675028205,
    "train_recon": 0.024009106738958508,
    "train_transition": 0.0020311098342062905,
    "train_dag": 0.0,
    "train_contrastive": 0.0,
    "val_total": 0.026697511385594095,
    "val_recon": 0.024886408022471836,
    "dag_constraint": 0.0,
    "time_s": 0.2527811527252197
  },
  {
    "epoch": 64,
    "train_total": 0.02610463893506676,
    "train_recon": 0.0240967731224373,
    "train_transition": 0.0020078660309081897,
    "train_dag": 0.0,
    "train_contrastive": 0.0,
    "val_total": 0.02616193358387266,
    "val_recon": 0.024383075003113066,
    "dag_constraint": 0.0,
    "time_s": 0.2529294490814209
  },
  {
    "epoch": 65,
    "train_total": 0.026069935061968863,
    "train_recon": 0.02407302870415151,
    "train_transition": 0.0019969065178884193,
    "train_dag": 0.0,
    "train_contrastive": 0.0,
    "val_total": 0.026168432352798327,
    "val_recon": 0.024447629494326457,
    "dag_constraint": 0.0,
    "time_s": 0.25138378143310547
  },
  {
    "epoch": 66,
    "train_total": 0.025799658033065498,
    "train_recon": 0.023843360249884427,
    "train_transition": 0.0019562977831810713,
    "train_dag": 0.0,
    "train_contrastive": 0.0,
    "val_total": 0.027939027175307274,
    "val_recon": 0.026092200140867914,
    "dag_constraint": 0.0,
    "time_s": 0.24681615829467773
  },
  {
    "epoch": 67,
    "train_total": 0.025892631616443396,
    "train_recon": 0.023998434888198972,
    "train_transition": 0.001894196742796339,
    "train_dag": 0.0,
    "train_contrastive": 0.0,
    "val_total": 0.02652755698987416,
    "val_recon": 0.024797463789582253,
    "dag_constraint": 0.0,
    "time_s": 0.2472524642944336
  },
  {
    "epoch": 68,
    "train_total": 0.02563720685429871,
    "train_recon": 0.023716261610388756,
    "train_transition": 0.0019209451565984637,
    "train_dag": 0.0,
    "train_contrastive": 0.0,
    "val_total": 0.02654491551220417,
    "val_recon": 0.024884326649563655,
    "dag_constraint": 0.0,
    "time_s": 0.24691057205200195
  },
  {
    "epoch": 69,
    "train_total": 0.026143357797991484,
    "train_recon": 0.02419561630813405,
    "train_transition": 0.0019477413879940286,
    "train_dag": 0.0,
    "train_contrastive": 0.0,
    "val_total": 0.02593887730368546,
    "val_recon": 0.024248598409550532,
    "dag_constraint": 0.0,
    "time_s": 0.24976873397827148
  },
  {
    "epoch": 70,
    "train_total": 0.02559509506681934,
    "train_recon": 0.023720377357676625,
    "train_transition": 0.001874717665486969,
    "train_dag": 0.0,
    "train_contrastive": 0.0,
    "val_total": 0.026819709156240736,
    "val_recon": 0.025090810975858142,
    "dag_constraint": 0.0,
    "time_s": 0.2504851818084717
  },
  {
    "epoch": 71,
    "train_total": 0.025580332905519754,
    "train_recon": 0.023737923183944076,
    "train_transition": 0.0018424097506795079,
    "train_dag": 0.0,
    "train_contrastive": 0.0,
    "val_total": 0.025899091735482216,
    "val_recon": 0.024226163380912373,
    "dag_constraint": 0.0,
    "time_s": 0.2551405429840088
  },
  {
    "epoch": 72,
    "train_total": 0.025719539320562035,
    "train_recon": 0.02388038922799751,
    "train_transition": 0.0018391500052530318,
    "train_dag": 0.0,
    "train_contrastive": 0.0,
    "val_total": 0.02581342895116125,
    "val_recon": 0.02415190770157746,
    "dag_constraint": 0.0,
    "time_s": 0.2499544620513916
  },
  {
    "epoch": 73,
    "train_total": 0.02531773125519976,
    "train_recon": 0.02352630568202585,
    "train_transition": 0.0017914253694470972,
    "train_dag": 0.0,
    "train_contrastive": 0.0,
    "val_total": 0.02614687250128814,
    "val_recon": 0.02454298867710999,
    "dag_constraint": 0.0,
    "time_s": 0.2577781677246094
  },
  {
    "epoch": 74,
    "train_total": 0.026380123221315444,
    "train_recon": 0.024529433401767164,
    "train_transition": 0.0018506897758925334,
    "train_dag": 0.0,
    "train_contrastive": 0.0,
    "val_total": 0.026169151067733765,
    "val_recon": 0.024501546153000424,
    "dag_constraint": 0.0,
    "time_s": 0.2581968307495117
  },
  {
    "epoch": 75,
    "train_total": 0.025592052494175732,
    "train_recon": 0.023789733881130815,
    "train_transition": 0.0018023187440121546,
    "train_dag": 0.0,
    "train_contrastive": 0.0,
    "val_total": 0.026135322770902088,
    "val_recon": 0.024535069508211955,
    "dag_constraint": 0.0,
    "time_s": 0.25746893882751465
  },
  {
    "epoch": 76,
    "train_total": 0.025172447494696826,
    "train_recon": 0.02346122160088271,
    "train_transition": 0.0017112259374698624,
    "train_dag": 0.0,
    "train_contrastive": 0.0,
    "val_total": 0.026198594963976314,
    "val_recon": 0.02457362972199917,
    "dag_constraint": 0.0,
    "time_s": 0.25117945671081543
  },
  {
    "epoch": 77,
    "train_total": 0.02544321387540549,
    "train_recon": 0.02369563578395173,
    "train_transition": 0.001747577975038439,
    "train_dag": 0.0,
    "train_contrastive": 0.0,
    "val_total": 0.025740473664232662,
    "val_recon": 0.024183494970202446,
    "dag_constraint": 0.0,
    "time_s": 0.25383591651916504
  },
  {
    "epoch": 78,
    "train_total": 0.025289513519965112,
    "train_recon": 0.02358023211127147,
    "train_transition": 0.0017092815542127937,
    "train_dag": 0.0,
    "train_contrastive": 0.0,
    "val_total": 0.025720379980547086,
    "val_recon": 0.02406625635921955,
    "dag_constraint": 0.0,
    "time_s": 0.2507054805755615
  },
  {
    "epoch": 79,
    "train_total": 0.025407777982763946,
    "train_recon": 0.023680419952142984,
    "train_transition": 0.0017273581470362842,
    "train_dag": 0.0,
    "train_contrastive": 0.0,
    "val_total": 0.027252027232732092,
    "val_recon": 0.025553940928408077,
    "dag_constraint": 0.0,
    "time_s": 0.25128936767578125
  },
  {
    "epoch": 80,
    "train_total": 0.02593558357330039,
    "train_recon": 0.024165460548829287,
    "train_transition": 0.0017701232864055783,
    "train_dag": 0.0,
    "train_contrastive": 0.0,
    "val_total": 0.025835551853690828,
    "val_recon": 0.024288962728210857,
    "dag_constraint": 0.0,
    "time_s": 0.2521193027496338
  },
  {
    "epoch": 81,
    "train_total": 0.025429949164390564,
    "train_recon": 0.023711321293376386,
    "train_transition": 0.0017186279583256692,
    "train_dag": 0.0,
    "train_contrastive": 0.0,
    "val_total": 0.026468494640929357,
    "val_recon": 0.02487431706062385,
    "dag_constraint": 0.0,
    "time_s": 0.2509944438934326
  },
  {
    "epoch": 82,
    "train_total": 0.025271758320741355,
    "train_recon": 0.023592383484356105,
    "train_transition": 0.0016793746908660978,
    "train_dag": 0.0,
    "train_contrastive": 0.0,
    "val_total": 0.02541522734931537,
    "val_recon": 0.02390726309801851,
    "dag_constraint": 0.0,
    "time_s": 0.2562980651855469
  },
  {
    "epoch": 83,
    "train_total": 0.024893058696761727,
    "train_recon": 0.02326283318689093,
    "train_transition": 0.0016302253643516451,
    "train_dag": 0.0,
    "train_contrastive": 0.0,
    "val_total": 0.025630165157573565,
    "val_recon": 0.024121621091450964,
    "dag_constraint": 0.0,
    "time_s": 0.25704407691955566
  },
  {
    "epoch": 84,
    "train_total": 0.02512935461709276,
    "train_recon": 0.02346226153895259,
    "train_transition": 0.0016670931945554912,
    "train_dag": 0.0,
    "train_contrastive": 0.0,
    "val_total": 0.025464767856257304,
    "val_recon": 0.02397734166256019,
    "dag_constraint": 0.0,
    "time_s": 0.25429677963256836
  },
  {
    "epoch": 85,
    "train_total": 0.024916149501223117,
    "train_recon": 0.023315742088016123,
    "train_transition": 0.0016004075441742316,
    "train_dag": 0.0,
    "train_contrastive": 0.0,
    "val_total": 0.025444218622786657,
    "val_recon": 0.02396665353860174,
    "dag_constraint": 0.0,
    "time_s": 0.2605898380279541
  },
  {
    "epoch": 86,
    "train_total": 0.025488441810011864,
    "train_recon": 0.023830273072235286,
    "train_transition": 0.0016581688105361536,
    "train_dag": 0.0,
    "train_contrastive": 0.0,
    "val_total": 0.026598464431507245,
    "val_recon": 0.025074104645422528,
    "dag_constraint": 0.0,
    "time_s": 0.250598669052124
  },
  {
    "epoch": 87,
    "train_total": 0.02548738452605903,
    "train_recon": 0.023831696656998247,
    "train_transition": 0.0016556876071263105,
    "train_dag": 0.0,
    "train_contrastive": 0.0,
    "val_total": 0.026249121874570847,
    "val_recon": 0.024727498314210346,
    "dag_constraint": 0.0,
    "time_s": 0.25708675384521484
  },
  {
    "epoch": 88,
    "train_total": 0.025379795231856406,
    "train_recon": 0.023740712145809084,
    "train_transition": 0.0016390831588068977,
    "train_dag": 0.0,
    "train_contrastive": 0.0,
    "val_total": 0.02524466147380216,
    "val_recon": 0.023800726713878766,
    "dag_constraint": 0.0,
    "time_s": 0.2543983459472656
  },
  {
    "epoch": 89,
    "train_total": 0.02491198811912909,
    "train_recon": 0.02334424405125901,
    "train_transition": 0.001567744286148809,
    "train_dag": 0.0,
    "train_contrastive": 0.0,
    "val_total": 0.025609826935189112,
    "val_recon": 0.02412944020969527,
    "dag_constraint": 0.0,
    "time_s": 0.2549099922180176
  },
  {
    "epoch": 90,
    "train_total": 0.024956438515800983,
    "train_recon": 0.023392796865664423,
    "train_transition": 0.001563641766551882,
    "train_dag": 0.0,
    "train_contrastive": 0.0,
    "val_total": 0.025157696434429715,
    "val_recon": 0.02372402884066105,
    "dag_constraint": 0.0,
    "time_s": 0.2574636936187744
  },
  {
    "epoch": 91,
    "train_total": 0.025126240157987922,
    "train_recon": 0.02353928709635511,
    "train_transition": 0.0015869532799115404,
    "train_dag": 0.0,
    "train_contrastive": 0.0,
    "val_total": 0.025561047984021052,
    "val_recon": 0.024106651012386595,
    "dag_constraint": 0.0,
    "time_s": 0.2494204044342041
  },
  {
    "epoch": 92,
    "train_total": 0.024597589450422674,
    "train_recon": 0.02305273903766647,
    "train_transition": 0.0015448505291715264,
    "train_dag": 0.0,
    "train_contrastive": 0.0,
    "val_total": 0.02539229073694774,
    "val_recon": 0.023995216137596538,
    "dag_constraint": 0.0,
    "time_s": 0.25246357917785645
  },
  {
    "epoch": 93,
    "train_total": 0.02475648029940203,
    "train_recon": 0.02321647887583822,
    "train_transition": 0.001540001350804232,
    "train_dag": 0.0,
    "train_contrastive": 0.0,
    "val_total": 0.02533463841038091,
    "val_recon": 0.02397482150367328,
    "dag_constraint": 0.0,
    "time_s": 0.2514176368713379
  },
  {
    "epoch": 94,
    "train_total": 0.02476782031590119,
    "train_recon": 0.02323843806516379,
    "train_transition": 0.001529382192529738,
    "train_dag": 0.0,
    "train_contrastive": 0.0,
    "val_total": 0.02516189669924123,
    "val_recon": 0.023804955716644014,
    "dag_constraint": 0.0,
    "time_s": 0.24697661399841309
  },
  {
    "epoch": 95,
    "train_total": 0.024704405514057726,
    "train_recon": 0.0231923270621337,
    "train_transition": 0.0015120783064048737,
    "train_dag": 0.0,
    "train_contrastive": 0.0,
    "val_total": 0.02521458560866969,
    "val_recon": 0.023881608620285988,
    "dag_constraint": 0.0,
    "time_s": 0.24732160568237305
  },
  {
    "epoch": 96,
    "train_total": 0.02497886383207515,
    "train_recon": 0.0234562941477634,
    "train_transition": 0.0015225697425194085,
    "train_dag": 0.0,
    "train_contrastive": 0.0,
    "val_total": 0.025890250291143144,
    "val_recon": 0.02451345617217677,
    "dag_constraint": 0.0,
    "time_s": 0.24769330024719238
  },
  {
    "epoch": 97,
    "train_total": 0.024852902337443084,
    "train_recon": 0.023339284060057253,
    "train_transition": 0.0015136183064896613,
    "train_dag": 0.0,
    "train_contrastive": 0.0,
    "val_total": 0.024896816749657904,
    "val_recon": 0.023564466142228672,
    "dag_constraint": 0.0,
    "time_s": 0.24950838088989258
  },
  {
    "epoch": 98,
    "train_total": 0.02481609320966527,
    "train_recon": 0.023309759213589132,
    "train_transition": 0.0015063341415952891,
    "train_dag": 0.0,
    "train_contrastive": 0.0,
    "val_total": 0.027041842628802572,
    "val_recon": 0.025529217773250172,
    "dag_constraint": 0.0,
    "time_s": 0.25127410888671875
  },
  {
    "epoch": 99,
    "train_total": 0.024981694121379405,
    "train_recon": 0.023485452169552445,
    "train_transition": 0.001496241966378875,
    "train_dag": 0.0,
    "train_contrastive": 0.0,
    "val_total": 0.024951588628547534,
    "val_recon": 0.023570695891976357,
    "dag_constraint": 0.0,
    "time_s": 0.2472231388092041
  },
  {
    "epoch": 100,
    "train_total": 0.024495440651662648,
    "train_recon": 0.023023567046038806,
    "train_transition": 0.0014718736638315022,
    "train_dag": 0.0,
    "train_contrastive": 0.0,
    "val_total": 0.026038632595113347,
    "val_recon": 0.024641838989087513,
    "dag_constraint": 0.0,
    "time_s": 0.24821138381958008
  },
  {
    "epoch": 101,
    "train_total": 0.024879869364667684,
    "train_recon": 0.023419590084813535,
    "train_transition": 0.0014602791488869116,
    "train_dag": 0.0,
    "train_contrastive": 0.0,
    "val_total": 0.02471057724739824,
    "val_recon": 0.023392543462770327,
    "dag_constraint": 0.0,
    "time_s": 0.2503776550292969
  },
  {
    "epoch": 102,
    "train_total": 0.024478424864355475,
    "train_recon": 0.02301592065487057,
    "train_transition": 0.0014625041949329898,
    "train_dag": 0.0,
    "train_contrastive": 0.0,
    "val_total": 0.026029120598520552,
    "val_recon": 0.024663691009793962,
    "dag_constraint": 0.0,
    "time_s": 0.24756121635437012
  },
  {
    "epoch": 103,
    "train_total": 0.02448342036223039,
    "train_recon": 0.023051889438647777,
    "train_transition": 0.001431530952686444,
    "train_dag": 0.0,
    "train_contrastive": 0.0,
    "val_total": 0.02473062090575695,
    "val_recon": 0.023421680820839747,
    "dag_constraint": 0.0,
    "time_s": 0.2458658218383789
  },
  {
    "epoch": 104,
    "train_total": 0.024370080733206123,
    "train_recon": 0.02295910898828879,
    "train_transition": 0.0014109717885730788,
    "train_dag": 0.0,
    "train_contrastive": 0.0,
    "val_total": 0.024795073217579296,
    "val_recon": 0.023479140496679714,
    "dag_constraint": 0.0,
    "time_s": 0.24901223182678223
  },
  {
    "epoch": 105,
    "train_total": 0.024466969829518348,
    "train_recon": 0.023026108101475984,
    "train_transition": 0.0014408617571461946,
    "train_dag": 0.0,
    "train_contrastive": 0.0,
    "val_total": 0.02471614575811795,
    "val_recon": 0.02347278967499733,
    "dag_constraint": 0.0,
    "time_s": 0.24977898597717285
  },
  {
    "epoch": 106,
    "train_total": 0.024518983031157404,
    "train_recon": 0.023141295881941915,
    "train_transition": 0.0013776873238384724,
    "train_dag": 0.0,
    "train_contrastive": 0.0,
    "val_total": 0.02532276963549001,
    "val_recon": 0.023939238595111028,
    "dag_constraint": 0.0,
    "time_s": 0.2464604377746582
  },
  {
    "epoch": 107,
    "train_total": 0.02443552896147594,
    "train_recon": 0.02303365431725979,
    "train_transition": 0.001401874513248913,
    "train_dag": 0.0,
    "train_contrastive": 0.0,
    "val_total": 0.024800180856670653,
    "val_recon": 0.023524182715586255,
    "dag_constraint": 0.0,
    "time_s": 0.24628925323486328
  },
  {
    "epoch": 108,
    "train_total": 0.02411357912933454,
    "train_recon": 0.022734941099770367,
    "train_transition": 0.0013786380004603416,
    "train_dag": 0.0,
    "train_contrastive": 0.0,
    "val_total": 0.024727548605629375,
    "val_recon": 0.023471919553620473,
    "dag_constraint": 0.0,
    "time_s": 0.2457127571105957
  },
  {
    "epoch": 109,
    "train_total": 0.024190302356146276,
    "train_recon": 0.02281807828694582,
    "train_transition": 0.0013722240400966257,
    "train_dag": 0.0,
    "train_contrastive": 0.0,
    "val_total": 0.024655173665710857,
    "val_recon": 0.023433567423905646,
    "dag_constraint": 0.0,
    "time_s": 0.24849915504455566
  },
  {
    "epoch": 110,
    "train_total": 0.024167720053810626,
    "train_recon": 0.022829033725429326,
    "train_transition": 0.0013386864739004523,
    "train_dag": 0.0,
    "train_contrastive": 0.0,
    "val_total": 0.026891759995903288,
    "val_recon": 0.025458398940307752,
    "dag_constraint": 0.0,
    "time_s": 0.24868345260620117
  },
  {
    "epoch": 111,
    "train_total": 0.024850315821822733,
    "train_recon": 0.02346398524241522,
    "train_transition": 0.0013863306667190045,
    "train_dag": 0.0,
    "train_contrastive": 0.0,
    "val_total": 0.024763733414666995,
    "val_recon": 0.02352521462099893,
    "dag_constraint": 0.0,
    "time_s": 0.24764180183410645
  },
  {
    "epoch": 112,
    "train_total": 0.024207561975345016,
    "train_recon": 0.022882789722643793,
    "train_transition": 0.0013247723109088838,
    "train_dag": 0.0,
    "train_contrastive": 0.0,
    "val_total": 0.024477652673210417,
    "val_recon": 0.023235990798899105,
    "dag_constraint": 0.0,
    "time_s": 0.2517578601837158
  },
  {
    "epoch": 113,
    "train_total": 0.02447887836024165,
    "train_recon": 0.023109393194317818,
    "train_transition": 0.0013694852241314948,
    "train_dag": 0.0,
    "train_contrastive": 0.0,
    "val_total": 0.024779382294842174,
    "val_recon": 0.023531399401170865,
    "dag_constraint": 0.0,
    "time_s": 0.25917983055114746
  },
  {
    "epoch": 114,
    "train_total": 0.024251625582110137,
    "train_recon": 0.022896520444191992,
    "train_transition": 0.0013551050651585683,
    "train_dag": 0.0,
    "train_contrastive": 0.0,
    "val_total": 0.024600833920495852,
    "val_recon": 0.02339630334505013,
    "dag_constraint": 0.0,
    "time_s": 0.2548677921295166
  },
  {
    "epoch": 115,
    "train_total": 0.024203058856073767,
    "train_recon": 0.02288137300638482,
    "train_transition": 0.0013216859224485233,
    "train_dag": 0.0,
    "train_contrastive": 0.0,
    "val_total": 0.025626947837216512,
    "val_recon": 0.02434912004641124,
    "dag_constraint": 0.0,
    "time_s": 0.2513563632965088
  },
  {
    "epoch": 116,
    "train_total": 0.024659691844135523,
    "train_recon": 0.0233193397289142,
    "train_transition": 0.0013403521152213216,
    "train_dag": 0.0,
    "train_contrastive": 0.0,
    "val_total": 0.0251555253884622,
    "val_recon": 0.023915986929621016,
    "dag_constraint": 0.0,
    "time_s": 0.24780488014221191
  },
  {
    "epoch": 117,
    "train_total": 0.02443343069171533,
    "train_recon": 0.023089244845323265,
    "train_transition": 0.0013441857736324891,
    "train_dag": 0.0,
    "train_contrastive": 0.0,
    "val_total": 0.02463691442140511,
    "val_recon": 0.02340600160615785,
    "dag_constraint": 0.0,
    "time_s": 0.24811863899230957
  },
  {
    "epoch": 118,
    "train_total": 0.02433320606360212,
    "train_recon": 0.023016174149233848,
    "train_transition": 0.0013170318707125261,
    "train_dag": 0.0,
    "train_contrastive": 0.0,
    "val_total": 0.02537898878966059,
    "val_recon": 0.024143601368580545,
    "dag_constraint": 0.0,
    "time_s": 0.24627089500427246
  },
  {
    "epoch": 119,
    "train_total": 0.024399392947088927,
    "train_recon": 0.02305665158201009,
    "train_transition": 0.0013427412923192605,
    "train_dag": 0.0,
    "train_contrastive": 0.0,
    "val_total": 0.02494495707963194,
    "val_recon": 0.02373723446258477,
    "dag_constraint": 0.0,
    "time_s": 0.24713993072509766
  },
  {
    "epoch": 120,
    "train_total": 0.0241166531923227,
    "train_recon": 0.022819207923021168,
    "train_transition": 0.001297445414820686,
    "train_dag": 0.0,
    "train_contrastive": 0.0,
    "val_total": 0.025688566799674715,
    "val_recon": 0.024451657331415584,
    "dag_constraint": 0.0,
    "time_s": 0.24986696243286133
  },
  {
    "epoch": 121,
    "train_total": 0.024516141158528626,
    "train_recon": 0.023216184112243354,
    "train_transition": 0.0012999569589737803,
    "train_dag": 0.0,
    "train_contrastive": 0.0,
    "val_total": 0.0249161496758461,
    "val_recon": 0.02373898800994669,
    "dag_constraint": 0.0,
    "time_s": 0.2487943172454834
  },
  {
    "epoch": 122,
    "train_total": 0.023972888884600252,
    "train_recon": 0.02271411631954834,
    "train_transition": 0.0012587726960191503,
    "train_dag": 0.0,
    "train_contrastive": 0.0,
    "val_total": 0.025082954870803014,
    "val_recon": 0.023827588451760157,
    "dag_constraint": 0.0,
    "time_s": 0.25081825256347656
  },
  {
    "epoch": 123,
    "train_total": 0.024152640718966722,
    "train_recon": 0.022871582012157887,
    "train_transition": 0.0012810584157705307,
    "train_dag": 0.0,
    "train_contrastive": 0.0,
    "val_total": 0.02463207207620144,
    "val_recon": 0.02345319092273712,
    "dag_constraint": 0.0,
    "time_s": 0.24866867065429688
  },
  {
    "epoch": 124,
    "train_total": 0.024006019753869623,
    "train_recon": 0.022763439686968923,
    "train_transition": 0.0012425799504853785,
    "train_dag": 0.0,
    "train_contrastive": 0.0,
    "val_total": 0.024729826620646884,
    "val_recon": 0.023580207622476985,
    "dag_constraint": 0.0,
    "time_s": 0.24569106101989746
  },
  {
    "epoch": 125,
    "train_total": 0.02391809894470498,
    "train_recon": 0.022691728197969496,
    "train_transition": 0.0012263706012163311,
    "train_dag": 0.0,
    "train_contrastive": 0.0,
    "val_total": 0.024127316794225147,
    "val_recon": 0.022967086838824407,
    "dag_constraint": 0.0,
    "time_s": 0.25361156463623047
  },
  {
    "epoch": 126,
    "train_total": 0.023898306593764573,
    "train_recon": 0.022626388119533658,
    "train_transition": 0.0012719184160232544,
    "train_dag": 0.0,
    "train_contrastive": 0.0,
    "val_total": 0.0245903983180012,
    "val_recon": 0.023439217624919757,
    "dag_constraint": 0.0,
    "time_s": 0.24865961074829102
  },
  {
    "epoch": 127,
    "train_total": 0.023771373671479523,
    "train_recon": 0.022568672196939588,
    "train_transition": 0.0012027015181956813,
    "train_dag": 0.0,
    "train_contrastive": 0.0,
    "val_total": 0.02413667525563921,
    "val_recon": 0.023027499073318074,
    "dag_constraint": 0.0,
    "time_s": 0.24905061721801758
  },
  {
    "epoch": 128,
    "train_total": 0.02369699557311833,
    "train_recon": 0.022483161534182727,
    "train_transition": 0.0012138340389356017,
    "train_dag": 0.0,
    "train_contrastive": 0.0,
    "val_total": 0.024198739922472408,
    "val_recon": 0.02302243241242,
    "dag_constraint": 0.0,
    "time_s": 0.2495896816253662
  },
  {
    "epoch": 129,
    "train_total": 0.02427701564738527,
    "train_recon": 0.023011614626739174,
    "train_transition": 0.0012654010206460953,
    "train_dag": 0.0,
    "train_contrastive": 0.0,
    "val_total": 0.02393588423728943,
    "val_recon": 0.022782029850142344,
    "dag_constraint": 0.0,
    "time_s": 0.2495899200439453
  },
  {
    "epoch": 130,
    "train_total": 0.023785943747498095,
    "train_recon": 0.022587303130421788,
    "train_transition": 0.0011986407189397141,
    "train_dag": 0.0,
    "train_contrastive": 0.0,
    "val_total": 0.02394504818533148,
    "val_recon": 0.022835354187658856,
    "dag_constraint": 0.0,
    "time_s": 0.2507772445678711
  },
  {
    "epoch": 131,
    "train_total": 0.023646138550247997,
    "train_recon": 0.02243947790702805,
    "train_transition": 0.0012066604540450498,
    "train_dag": 0.0,
    "train_contrastive": 0.0,
    "val_total": 0.024075031280517578,
    "val_recon": 0.022949282878211567,
    "dag_constraint": 0.0,
    "time_s": 0.2489316463470459
  },
  {
    "epoch": 132,
    "train_total": 0.023909280193038285,
    "train_recon": 0.02268515742616728,
    "train_transition": 0.0012241229269420728,
    "train_dag": 0.0,
    "train_contrastive": 0.0,
    "val_total": 0.02436856659395354,
    "val_recon": 0.023260130680033138,
    "dag_constraint": 0.0,
    "time_s": 0.24632477760314941
  },
  {
    "epoch": 133,
    "train_total": 0.023653043201193213,
    "train_recon": 0.02245113835670054,
    "train_transition": 0.0012019049318041652,
    "train_dag": 0.0,
    "train_contrastive": 0.0,
    "val_total": 0.02405354247561523,
    "val_recon": 0.022978132856743678,
    "dag_constraint": 0.0,
    "time_s": 0.252086877822876
  },
  {
    "epoch": 134,
    "train_total": 0.02351784857455641,
    "train_recon": 0.022346619807649404,
    "train_transition": 0.0011712285631801933,
    "train_dag": 0.0,
    "train_contrastive": 0.0,
    "val_total": 0.024031711742281914,
    "val_recon": 0.022969564689057215,
    "dag_constraint": 0.0,
    "time_s": 0.2469942569732666
  },
  {
    "epoch": 135,
    "train_total": 0.023948303365614265,
    "train_recon": 0.02276498422725126,
    "train_transition": 0.001183319094707258,
    "train_dag": 0.0,
    "train_contrastive": 0.0,
    "val_total": 0.02432782681924956,
    "val_recon": 0.02325917673962457,
    "dag_constraint": 0.0,
    "time_s": 0.24721813201904297
  },
  {
    "epoch": 136,
    "train_total": 0.023845882271416485,
    "train_recon": 0.022666065429802984,
    "train_transition": 0.0011798168707173318,
    "train_dag": 0.0,
    "train_contrastive": 0.0,
    "val_total": 0.028667512482830455,
    "val_recon": 0.027362350108368055,
    "dag_constraint": 0.0,
    "time_s": 0.24800634384155273
  },
  {
    "epoch": 137,
    "train_total": 0.024767228052951396,
    "train_recon": 0.0235271870624274,
    "train_transition": 0.0012400409614201635,
    "train_dag": 0.0,
    "train_contrastive": 0.0,
    "val_total": 0.02474188937672547,
    "val_recon": 0.023624963526214873,
    "dag_constraint": 0.0,
    "time_s": 0.24724936485290527
  },
  {
    "epoch": 138,
    "train_total": 0.023923574248328805,
    "train_recon": 0.02272036945214495,
    "train_transition": 0.0012032048107357696,
    "train_dag": 0.0,
    "train_contrastive": 0.0,
    "val_total": 0.024135250066007887,
    "val_recon": 0.023032754925744876,
    "dag_constraint": 0.0,
    "time_s": 0.2519843578338623
  },
  {
    "epoch": 139,
    "train_total": 0.023611053416971117,
    "train_recon": 0.022455758007708937,
    "train_transition": 0.0011552954820217565,
    "train_dag": 0.0,
    "train_contrastive": 0.0,
    "val_total": 0.024484718484537944,
    "val_recon": 0.023364513580288206,
    "dag_constraint": 0.0,
    "time_s": 0.24500226974487305
  },
  {
    "epoch": 140,
    "train_total": 0.02414362458512187,
    "train_recon": 0.022910250234417617,
    "train_transition": 0.0012333743943599984,
    "train_dag": 0.0,
    "train_contrastive": 0.0,
    "val_total": 0.024236264505556653,
    "val_recon": 0.02314339924071516,
    "dag_constraint": 0.0,
    "time_s": 0.24643898010253906
  },
  {
    "epoch": 141,
    "train_total": 0.023628318158444017,
    "train_recon": 0.022465006506536156,
    "train_transition": 0.0011633116519078612,
    "train_dag": 0.0,
    "train_contrastive": 0.0,
    "val_total": 0.023888659264360155,
    "val_recon": 0.022848408137048994,
    "dag_constraint": 0.0,
    "time_s": 0.24738740921020508
  },
  {
    "epoch": 142,
    "train_total": 0.023553950246423483,
    "train_recon": 0.022373719606548548,
    "train_transition": 0.0011802305962191895,
    "train_dag": 0.0,
    "train_contrastive": 0.0,
    "val_total": 0.024404568331582204,
    "val_recon": 0.023309771237628802,
    "dag_constraint": 0.0,
    "time_s": 0.24989795684814453
  },
  {
    "epoch": 143,
    "train_total": 0.02349419251549989,
    "train_recon": 0.022363752650562674,
    "train_transition": 0.0011304398794891313,
    "train_dag": 0.0,
    "train_contrastive": 0.0,
    "val_total": 0.024226694500872066,
    "val_recon": 0.023142826344285692,
    "dag_constraint": 0.0,
    "time_s": 0.2468125820159912
  },
  {
    "epoch": 144,
    "train_total": 0.02366070286370814,
    "train_recon": 0.02249618264613673,
    "train_transition": 0.0011645201593637466,
    "train_dag": 0.0,
    "train_contrastive": 0.0,
    "val_total": 0.025082370532410487,
    "val_recon": 0.023992745205760002,
    "dag_constraint": 0.0,
    "time_s": 0.24785709381103516
  },
  {
    "epoch": 145,
    "train_total": 0.023650089802686125,
    "train_recon": 0.022514145355671644,
    "train_transition": 0.0011359442432876676,
    "train_dag": 0.0,
    "train_contrastive": 0.0,
    "val_total": 0.02366032770701817,
    "val_recon": 0.0226628269468035,
    "dag_constraint": 0.0,
    "time_s": 0.2516031265258789
  },
  {
    "epoch": 146,
    "train_total": 0.023547433724161237,
    "train_recon": 0.022409370285458863,
    "train_transition": 0.0011380634095985442,
    "train_dag": 0.0,
    "train_contrastive": 0.0,
    "val_total": 0.023699207497494563,
    "val_recon": 0.022649086213537624,
    "dag_constraint": 0.0,
    "time_s": 0.25474071502685547
  },
  {
    "epoch": 147,
    "train_total": 0.023702198057435453,
    "train_recon": 0.02254973619710654,
    "train_transition": 0.0011524618603289127,
    "train_dag": 0.0,
    "train_contrastive": 0.0,
    "val_total": 0.023883277284247533,
    "val_recon": 0.022870094382337162,
    "dag_constraint": 0.0,
    "time_s": 0.2480306625366211
  },
  {
    "epoch": 148,
    "train_total": 0.023628007678780705,
    "train_recon": 0.022490902396384627,
    "train_transition": 0.0011371050495654345,
    "train_dag": 0.0,
    "train_contrastive": 0.0,
    "val_total": 0.024719602029238428,
    "val_recon": 0.023675902347479547,
    "dag_constraint": 0.0,
    "time_s": 0.24585890769958496
  },
  {
    "epoch": 149,
    "train_total": 0.023789325554389507,
    "train_recon": 0.022678267676383257,
    "train_transition": 0.0011110579362139106,
    "train_dag": 0.0,
    "train_contrastive": 0.0,
    "val_total": 0.023862657802445546,
    "val_recon": 0.02283587652657713,
    "dag_constraint": 0.0,
    "time_s": 0.24945712089538574
  },
  {
    "epoch": 150,
    "train_total": 0.023600435990374535,
    "train_recon": 0.022470976342447102,
    "train_transition": 0.0011294597061350942,
    "train_dag": 0.0,
    "train_contrastive": 0.0,
    "val_total": 0.024002138525247574,
    "val_recon": 0.022960889286228588,
    "dag_constraint": 0.0,
    "time_s": 0.24365520477294922
  },
  {
    "epoch": 151,
    "train_total": 0.02372022799681872,
    "train_recon": 0.022577108757104725,
    "train_transition": 0.001143119268817827,
    "train_dag": 0.0,
    "train_contrastive": 0.0,
    "val_total": 0.023995215073227882,
    "val_recon": 0.022975288863692964,
    "dag_constraint": 0.0,
    "time_s": 0.24956917762756348
  },
  {
    "epoch": 152,
    "train_total": 0.02346432994818315,
    "train_recon": 0.022366235905792564,
    "train_transition": 0.0010980938968714327,
    "train_dag": 0.0,
    "train_contrastive": 0.0,
    "val_total": 0.024009145530206815,
    "val_recon": 0.022949633853776113,
    "dag_constraint": 0.0,
    "time_s": 0.24451112747192383
  },
  {
    "epoch": 153,
    "train_total": 0.023509533260948956,
    "train_recon": 0.022370894090272486,
    "train_transition": 0.0011386390688130632,
    "train_dag": 0.0,
    "train_contrastive": 0.0,
    "val_total": 0.02395827802164214,
    "val_recon": 0.022910546511411667,
    "dag_constraint": 0.0,
    "time_s": 0.25588369369506836
  },
  {
    "epoch": 154,
    "train_total": 0.023437402211129665,
    "train_recon": 0.022329481202177703,
    "train_transition": 0.0011079208925366402,
    "train_dag": 0.0,
    "train_contrastive": 0.0,
    "val_total": 0.024012455184544836,
    "val_recon": 0.022974743374756405,
    "dag_constraint": 0.0,
    "time_s": 0.25815248489379883
  },
  {
    "epoch": 155,
    "train_total": 0.02405113319400698,
    "train_recon": 0.022931871586479247,
    "train_transition": 0.0011192617239430547,
    "train_dag": 0.0,
    "train_contrastive": 0.0,
    "val_total": 0.024791999054806575,
    "val_recon": 0.023725861949580058,
    "dag_constraint": 0.0,
    "time_s": 0.26145052909851074
  },
  {
    "epoch": 156,
    "train_total": 0.02431889093713835,
    "train_recon": 0.023190134845208377,
    "train_transition": 0.0011287561210338026,
    "train_dag": 0.0,
    "train_contrastive": 0.0,
    "val_total": 0.024848827560033118,
    "val_recon": 0.02377780234175069,
    "dag_constraint": 0.0,
    "time_s": 0.24899697303771973
  },
  {
    "epoch": 157,
    "train_total": 0.02357416762970388,
    "train_recon": 0.02243723877472803,
    "train_transition": 0.001136928709456697,
    "train_dag": 0.0,
    "train_contrastive": 0.0,
    "val_total": 0.023863010640655245,
    "val_recon": 0.02283452477838312,
    "dag_constraint": 0.0,
    "time_s": 0.2523794174194336
  },
  {
    "epoch": 158,
    "train_total": 0.02324070641770959,
    "train_recon": 0.022168642200995237,
    "train_transition": 0.0010720643767854199,
    "train_dag": 0.0,
    "train_contrastive": 0.0,
    "val_total": 0.023553759391818727,
    "val_recon": 0.02251103600221021,
    "dag_constraint": 0.0,
    "time_s": 0.24992132186889648
  },
  {
    "epoch": 159,
    "train_total": 0.0233866207418032,
    "train_recon": 0.022289250511676073,
    "train_transition": 0.0010973701137118042,
    "train_dag": 0.0,
    "train_contrastive": 0.0,
    "val_total": 0.023723799469215528,
    "val_recon": 0.022714619923915182,
    "dag_constraint": 0.0,
    "time_s": 0.2469165325164795
  },
  {
    "epoch": 160,
    "train_total": 0.023032028984744102,
    "train_recon": 0.021977097261697054,
    "train_transition": 0.001054931737598963,
    "train_dag": 0.0,
    "train_contrastive": 0.0,
    "val_total": 0.024367421865463257,
    "val_recon": 0.02337803239268916,
    "dag_constraint": 0.0,
    "time_s": 0.25711774826049805
  },
  {
    "epoch": 161,
    "train_total": 0.023679457197431475,
    "train_recon": 0.022589087777305394,
    "train_transition": 0.0010903695219894871,
    "train_dag": 0.0,
    "train_contrastive": 0.0,
    "val_total": 0.024157200008630753,
    "val_recon": 0.023180294781923294,
    "dag_constraint": 0.0,
    "time_s": 0.24930095672607422
  },
  {
    "epoch": 162,
    "train_total": 0.023566193238366395,
    "train_recon": 0.022474227065686136,
    "train_transition": 0.0010919660417130217,
    "train_dag": 0.0,
    "train_contrastive": 0.0,
    "val_total": 0.023932047986558506,
    "val_recon": 0.02291567623615265,
    "dag_constraint": 0.0,
    "time_s": 0.2526514530181885
  },
  {
    "epoch": 163,
    "train_total": 0.023557601089123636,
    "train_recon": 0.022459948144387454,
    "train_transition": 0.0010976529156323522,
    "train_dag": 0.0,
    "train_contrastive": 0.0,
    "val_total": 0.02416861296764442,
    "val_recon": 0.02318739252431052,
    "dag_constraint": 0.0,
    "time_s": 0.2499561309814453
  },
  {
    "epoch": 164,
    "train_total": 0.023316516890190542,
    "train_recon": 0.022246522770728916,
    "train_transition": 0.0010699939593905583,
    "train_dag": 0.0,
    "train_contrastive": 0.0,
    "val_total": 0.02329790485756738,
    "val_recon": 0.022325515480978147,
    "dag_constraint": 0.0,
    "time_s": 0.24973630905151367
  },
  {
    "epoch": 165,
    "train_total": 0.023029344738461077,
    "train_recon": 0.02200467447983101,
    "train_transition": 0.0010246702877338976,
    "train_dag": 0.0,
    "train_contrastive": 0.0,
    "val_total": 0.02336727348821504,
    "val_recon": 0.02239482823227133,
    "dag_constraint": 0.0,
    "time_s": 0.24618864059448242
  },
  {
    "epoch": 166,
    "train_total": 0.023210395593196154,
    "train_recon": 0.02212138078175485,
    "train_transition": 0.001089014724129811,
    "train_dag": 0.0,
    "train_contrastive": 0.0,
    "val_total": 0.02407246907906873,
    "val_recon": 0.02305874946926321,
    "dag_constraint": 0.0,
    "time_s": 0.24934959411621094
  },
  {
    "epoch": 167,
    "train_total": 0.023516221903264523,
    "train_recon": 0.022447506489697844,
    "train_transition": 0.0010687152098398656,
    "train_dag": 0.0,
    "train_contrastive": 0.0,
    "val_total": 0.023447668179869652,
    "val_recon": 0.022464977577328682,
    "dag_constraint": 0.0,
    "time_s": 0.26085567474365234
  },
  {
    "epoch": 168,
    "train_total": 0.023130188114009798,
    "train_recon": 0.022107814205810428,
    "train_transition": 0.0010223739664070308,
    "train_dag": 0.0,
    "train_contrastive": 0.0,
    "val_total": 0.02306458886180605,
    "val_recon": 0.022134474345615933,
    "dag_constraint": 0.0,
    "time_s": 0.25641942024230957
  },
  {
    "epoch": 169,
    "train_total": 0.023174493049737066,
    "train_recon": 0.02213681151624769,
    "train_transition": 0.0010376814607298002,
    "train_dag": 0.0,
    "train_contrastive": 0.0,
    "val_total": 0.023563874353255545,
    "val_recon": 0.022568318992853165,
    "dag_constraint": 0.0,
    "time_s": 0.25185656547546387
  },
  {
    "epoch": 170,
    "train_total": 0.023290586017537862,
    "train_recon": 0.022239741403609514,
    "train_transition": 0.0010508445848245174,
    "train_dag": 0.0,
    "train_contrastive": 0.0,
    "val_total": 0.024429326078721454,
    "val_recon": 0.023400463429944857,
    "dag_constraint": 0.0,
    "time_s": 0.25587940216064453
  },
  {
    "epoch": 171,
    "train_total": 0.023555977328214794,
    "train_recon": 0.02247218374395743,
    "train_transition": 0.0010837936133611947,
    "train_dag": 0.0,
    "train_contrastive": 0.0,
    "val_total": 0.023697343787976673,
    "val_recon": 0.022730215319565365,
    "dag_constraint": 0.0,
    "time_s": 0.2522461414337158
  },
  {
    "epoch": 172,
    "train_total": 0.02332358033163473,
    "train_recon": 0.0222845227108337,
    "train_transition": 0.001039057708112523,
    "train_dag": 0.0,
    "train_contrastive": 0.0,
    "val_total": 0.023786227351852825,
    "val_recon": 0.02281822290803705,
    "dag_constraint": 0.0,
    "time_s": 0.25296950340270996
  },
  {
    "epoch": 173,
    "train_total": 0.023481036419980228,
    "train_recon": 0.02245454234071076,
    "train_transition": 0.0010264939483022317,
    "train_dag": 0.0,
    "train_contrastive": 0.0,
    "val_total": 0.023403752063001906,
    "val_recon": 0.022477850584047183,
    "dag_constraint": 0.0,
    "time_s": 0.25409555435180664
  },
  {
    "epoch": 174,
    "train_total": 0.02317986375419423,
    "train_recon": 0.02213582821423188,
    "train_transition": 0.0010440355690661818,
    "train_dag": 0.0,
    "train_contrastive": 0.0,
    "val_total": 0.023094721670661653,
    "val_recon": 0.022173453122377396,
    "dag_constraint": 0.0,
    "time_s": 0.25554347038269043
  },
  {
    "epoch": 175,
    "train_total": 0.023066240071784705,
    "train_recon": 0.0220429107430391,
    "train_transition": 0.0010233293432975188,
    "train_dag": 0.0,
    "train_contrastive": 0.0,
    "val_total": 0.023418238386511803,
    "val_recon": 0.022500612639955113,
    "dag_constraint": 0.0,
    "time_s": 0.2506725788116455
  },
  {
    "epoch": 176,
    "train_total": 0.023215688299387693,
    "train_recon": 0.022219659644179046,
    "train_transition": 0.0009960286552086473,
    "train_dag": 0.0,
    "train_contrastive": 0.0,
    "val_total": 0.023353970742651393,
    "val_recon": 0.022435581577675685,
    "dag_constraint": 0.0,
    "time_s": 0.2515573501586914
  },
  {
    "epoch": 177,
    "train_total": 0.022874540532939136,
    "train_recon": 0.02185502153588459,
    "train_transition": 0.0010195190989179537,
    "train_dag": 0.0,
    "train_contrastive": 0.0,
    "val_total": 0.02328696022076266,
    "val_recon": 0.02237010800412723,
    "dag_constraint": 0.0,
    "time_s": 0.25289487838745117
  },
  {
    "epoch": 178,
    "train_total": 0.023222306394018233,
    "train_recon": 0.0221737630199641,
    "train_transition": 0.0010485434613656253,
    "train_dag": 0.0,
    "train_contrastive": 0.0,
    "val_total": 0.023360954331500188,
    "val_recon": 0.022411694484097616,
    "dag_constraint": 0.0,
    "time_s": 0.25565266609191895
  },
  {
    "epoch": 179,
    "train_total": 0.023112073889933527,
    "train_recon": 0.022111395839601755,
    "train_transition": 0.0010006781667470932,
    "train_dag": 0.0,
    "train_contrastive": 0.0,
    "val_total": 0.02331648421074663,
    "val_recon": 0.022381288398589407,
    "dag_constraint": 0.0,
    "time_s": 0.25236940383911133
  },
  {
    "epoch": 180,
    "train_total": 0.02277250320184976,
    "train_recon": 0.02178144350182265,
    "train_transition": 0.0009910597145790234,
    "train_dag": 0.0,
    "train_contrastive": 0.0,
    "val_total": 0.023712607898882458,
    "val_recon": 0.02276857676250594,
    "dag_constraint": 0.0,
    "time_s": 0.250455379486084
  },
  {
    "epoch": 181,
    "train_total": 0.022990305500570685,
    "train_recon": 0.021985555998981,
    "train_transition": 0.001004749516141601,
    "train_dag": 0.0,
    "train_contrastive": 0.0,
    "val_total": 0.02324991620012692,
    "val_recon": 0.022316523428474153,
    "dag_constraint": 0.0,
    "time_s": 0.2510247230529785
  },
  {
    "epoch": 182,
    "train_total": 0.023103390005417168,
    "train_recon": 0.0221061161137186,
    "train_transition": 0.0009972737752832472,
    "train_dag": 0.0,
    "train_contrastive": 0.0,
    "val_total": 0.023306526243686676,
    "val_recon": 0.022371241822838783,
    "dag_constraint": 0.0,
    "time_s": 0.2523829936981201
  },
  {
    "epoch": 183,
    "train_total": 0.023166733095422387,
    "train_recon": 0.022165264934301376,
    "train_transition": 0.0010014682484325022,
    "train_dag": 0.0,
    "train_contrastive": 0.0,
    "val_total": 0.02416641531246049,
    "val_recon": 0.02319536597601005,
    "dag_constraint": 0.0,
    "time_s": 0.251812219619751
  },
  {
    "epoch": 184,
    "train_total": 0.023394561023451388,
    "train_recon": 0.02236487960908562,
    "train_transition": 0.0010296815307810903,
    "train_dag": 0.0,
    "train_contrastive": 0.0,
    "val_total": 0.024165944595422064,
    "val_recon": 0.023189807310700417,
    "dag_constraint": 0.0,
    "time_s": 0.25314998626708984
  },
  {
    "epoch": 185,
    "train_total": 0.02322158945025876,
    "train_recon": 0.02219294384121895,
    "train_transition": 0.0010286456381436437,
    "train_dag": 0.0,
    "train_contrastive": 0.0,
    "val_total": 0.02354008491550173,
    "val_recon": 0.02260917318718774,
    "dag_constraint": 0.0,
    "time_s": 0.2523062229156494
  },
  {
    "epoch": 186,
    "train_total": 0.022805967484600842,
    "train_recon": 0.02182313270168379,
    "train_transition": 0.0009828347974689677,
    "train_dag": 0.0,
    "train_contrastive": 0.0,
    "val_total": 0.023718062522155896,
    "val_recon": 0.02277452472065176,
    "dag_constraint": 0.0,
    "time_s": 0.25345730781555176
  },
  {
    "epoch": 187,
    "train_total": 0.022946788580156863,
    "train_recon": 0.021962243132293224,
    "train_transition": 0.0009845454478636384,
    "train_dag": 0.0,
    "train_contrastive": 0.0,
    "val_total": 0.023515396884509494,
    "val_recon": 0.022565416725618497,
    "dag_constraint": 0.0,
    "time_s": 0.25162434577941895
  },
  {
    "epoch": 188,
    "train_total": 0.02323897188762203,
    "train_recon": 0.022234301432035863,
    "train_transition": 0.0010046706447610632,
    "train_dag": 0.0,
    "train_contrastive": 0.0,
    "val_total": 0.0234868728688785,
    "val_recon": 0.02256611468536513,
    "dag_constraint": 0.0,
    "time_s": 0.2523934841156006
  }
]